[
  {
    "code": "2801430300",
    "original_codes": [
      "2801430100",
      "2801430200",
      "2801430300"
    ],
    "description": "SHOCK ABSORBER PIN - BEKO 2801430300 Ø14mm.",
    "image_url": "http://omniacomponents.s3.eu-west-1.amazonaws.com/images/lambdaresized/500x500/loghi_marchio/Arcelik/arcelik-beko.jpg"
  },
  {
    "code": "SAR026AC",
    "original_codes": [
      "2810430400"
    ],
    "description": "SHOCK ABSORBER - ARCELIK 90N 2810430400 - CIMA90N. Holes: Ø11+11mm. Fixing holes:  163/253mm",
    "image_url": "http://omniacomponents.s3.eu-west-1.amazonaws.com/images/lambdaresized/500x500/LAVAGGIO/31_Ammortizzatori-balestre/SAR026AC.jpg"
  },
  {
    "code": "SAR024AC",
    "original_codes": [
      "2810430900"
    ],
    "description": "SHOCK ABSORBER - ARCELIK 110N 2810430900 - CIMA110N. Holes: Ø12+12mm. Fixing holes:  190/285mm",
    "image_url": "http://omniacomponents.s3.eu-west-1.amazonaws.com/images/lambdaresized/500x500/LAVAGGIO/31_Ammortizzatori-balestre/SAR024AC.jpg"
  },
  {
    "code": "SAR000CY",
    "original_codes": [
      "481246648093",
      "481946648115",
      "92262039",
      "92697838"
    ],
    "description": "FRICTION PAD - CANDY 92697838",
    "image_url": "http://omniacomponents.s3.eu-west-1.amazonaws.com/images/lambdaresized/500x500/LAVAGGIO/31_Ammortizzatori-balestre/SAR000CY.jpg"
  },
  {
    "code": "SAR002ZN",
    "original_codes": [
      "1260038508",
      "1260038516",
      "1260624018",
      "1260624026",
      "1260636004",
      "1268832712",
      "1326240015",
      "3794303010"
    ],
    "description": "SHOCK ABSORBER 80N SHORT - ZANUSSI 379430301080N. Fixing holes: max 242mm, min 164mm. Holes:  Ø11+11mm.",
    "image_url": "http://omniacomponents.s3.eu-west-1.amazonaws.com/images/lambdaresized/500x500/LAVAGGIO/31_Ammortizzatori-balestre/SAR002ZN.jpg"
  },
  {
    "code": "SAR025ZN",
    "original_codes": [
      "1292348503",
      "1292348511",
      "8996454254385"
    ],
    "description": "SHOCK ABSORBER 60N LONG - ZANUSSI 129234851160N, long type. Holes: Ø10+10mm. Fixing holes:  274mm, min. 184mm.",
    "image_url": "http://omniacomponents.s3.eu-west-1.amazonaws.com/images/lambdaresized/500x500/LAVAGGIO/31_Ammortizzatori-balestre/SAR025ZN.jpg"
  },
  {
    "code": "SAR002VE",
    "original_codes": [
      "47004427"
    ],
    "description": "SHOCK ABSORBER 80N - VESTEL 4700442780N, holes:  Ø11+11mm.",
    "image_url": "http://omniacomponents.s3.eu-west-1.amazonaws.com/images/lambdaresized/500x500/LAVAGGIO/31_Ammortizzatori-balestre/SAR002VE.jpg"
  },
  {
    "code": "SAR016AC",
    "original_codes": [
      "2816870900"
    ],
    "description": "SHOCK ABSORBER 85N - ARCELIK-BEKO 281687090085N, holes:  Ø12,5+12,5mm.",
    "image_url": "http://omniacomponents.s3.eu-west-1.amazonaws.com/images/lambdaresized/500x500/LAVAGGIO/31_Ammortizzatori-balestre/SAR016AC.jpg"
  },
  {
    "code": "SAR005LG",
    "original_codes": [
      "4901ER2003D"
    ],
    "description": "SHOCK ABSORBER 40N - LG 4901ER2003D - AKS40N. Holes: Ø11+Ø11mm. Length: min. 167mm,  max.260mm.",
    "image_url": "http://omniacomponents.s3.eu-west-1.amazonaws.com/images/lambdaresized/500x500/LAVAGGIO/31_Ammortizzatori-balestre/SAR005LG.jpg"
  },
  {
    "code": "SAR016ZN",
    "original_codes": [
      "1322553601",
      "1322553700",
      "1327440002",
      "1327440028"
    ],
    "description": "SHOCK ABSORBER 60N - ZANUSSI 132255360160N. Length: max. 217mm, min. 150mm. Holes:  Ø11+11mm.",
    "image_url": "http://omniacomponents.s3.eu-west-1.amazonaws.com/images/lambdaresized/500x500/LAVAGGIO/31_Ammortizzatori-balestre/SAR016ZN.jpg"
  },
  {
    "code": "SAR018ZN",
    "original_codes": [
      "132255352",
      "132255383"
    ],
    "description": "SHOCK ABSORBER 60N - ZANUSSI 13225535260N. Length: max. 240mm, min. 163mm. Holes:  Ø11+11mm.",
    "image_url": "http://omniacomponents.s3.eu-west-1.amazonaws.com/images/lambdaresized/500x500/LAVAGGIO/31_Ammortizzatori-balestre/SAR018ZN.jpg"
  },
  {
    "code": "SAR004GO",
    "original_codes": [
      "111818"
    ],
    "description": "SHOCK ABSORBER 120N - GORENJE 111818 - ORIGINAL120N. Holes: Ø11+8mm. Length: min 172mm, max. 265m m.",
    "image_url": "http://omniacomponents.s3.eu-west-1.amazonaws.com/images/lambdaresized/500x500/LAVAGGIO/31_Ammortizzatori-balestre/SAR004GO.jpg"
  },
  {
    "code": "SAR004ID",
    "original_codes": [
      "140744"
    ],
    "description": "SHOCK ABSORBER 100N - INDESIT 140744 - CIMA100N, hole Ø13mm, lenght  225mm.",
    "image_url": "http://omniacomponents.s3.eu-west-1.amazonaws.com/images/lambdaresized/500x500/LAVAGGIO/31_Ammortizzatori-balestre/SAR004ID.jpg"
  },
  {
    "code": "SAR023ZN",
    "original_codes": [
      "1322553700",
      "1327440028"
    ],
    "description": "SHOCK ABSORBER 60N - ZANUSSI 1327440002 - AKS - UNTIL STOCK LAST60N. Length: max. 217mm, min. 150mm. Holes:  Ø11+11mm.",
    "image_url": "http://omniacomponents.s3.eu-west-1.amazonaws.com/images/lambdaresized/500x500/LAVAGGIO/31_Ammortizzatori-balestre/SAR023ZN.jpg"
  },
  {
    "code": "SAR013AC",
    "original_codes": [
      "2816870600"
    ],
    "description": "SHOCK ABSORBER 110N - ARCELIK - BEKO 2816870600110N, holes:  Ø12,5+12,5mm.",
    "image_url": "http://omniacomponents.s3.eu-west-1.amazonaws.com/images/lambdaresized/500x500/LAVAGGIO/31_Ammortizzatori-balestre/SAR013AC.jpg"
  },
  {
    "code": "SAR003ZN",
    "original_codes": [
      "1240172104",
      "132255300",
      "1322553007",
      "132255301",
      "1322553015",
      "146620002",
      "89964544258683"
    ],
    "description": "SHOCK ABSORBER 80N LONG - ZANUSSI 132255301580N, long. Fixing holes: max 274mm, min 184.  Holes: Ø11+11mm.",
    "image_url": "http://omniacomponents.s3.eu-west-1.amazonaws.com/images/lambdaresized/500x500/LAVAGGIO/31_Ammortizzatori-balestre/SAR003ZN.jpg"
  },
  {
    "code": "SAR000ZN",
    "original_codes": [
      "1260636012"
    ],
    "description": "SHOCK ABSORBER 60N SHORT - ZANUSSI 1260636012White. 60N, short type. Holes: Ø11+11mm. Fixing holes: 165/240mm.",
    "image_url": "http://omniacomponents.s3.eu-west-1.amazonaws.com/images/lambdaresized/500x500/LAVAGGIO/31_Ammortizzatori-balestre/SAR000ZN.jpg"
  },
  {
    "code": "SAR005ZN",
    "original_codes": [
      "41017168",
      "41017170",
      "41018714",
      "90488713"
    ],
    "description": "SHOCK ABSORBER 120N LONG - ZANUSSI-CANDY 41017168Long. 120N. Holes: Ø11+Ø11mm. Fixing holes: 183/26 8mm.",
    "image_url": "http://omniacomponents.s3.eu-west-1.amazonaws.com/images/lambdaresized/500x500/LAVAGGIO/31_Ammortizzatori-balestre/SAR005ZN.jpg"
  },
  {
    "code": "SAR011ZN",
    "original_codes": [
      "1322553007"
    ],
    "description": "SHOCK ABSORBER 80N SHORT - ZANUSSI 132255300780N, Length: 280mm. Hole:  Ø10mm.",
    "image_url": "http://omniacomponents.s3.eu-west-1.amazonaws.com/images/lambdaresized/500x500/LAVAGGIO/31_Ammortizzatori-balestre/SAR011ZN.jpg"
  },
  {
    "code": "SAR006SA",
    "original_codes": [
      "DC66-00343G"
    ],
    "description": "SHOCK ABSORBER 100N - SAMSUNG DC66-00343G - AKS100N, holes: Ø10+10mm. Length: min. 193mm, max.  300mm.",
    "image_url": "http://omniacomponents.s3.eu-west-1.amazonaws.com/images/lambdaresized/500x500/LAVAGGIO/31_Ammortizzatori-balestre/SAR006SA.jpg"
  },
  {
    "code": "SAR011AC",
    "original_codes": [
      "2816870200"
    ],
    "description": "SHOCK ABSORBER 110N - ARCELIK - BEKO 2816870200110N, holes: Ø11+11mm. Lenght: min. 185mm, max.  260mm.",
    "image_url": "http://omniacomponents.s3.eu-west-1.amazonaws.com/images/lambdaresized/500x500/LAVAGGIO/31_Ammortizzatori-balestre/SAR011AC.jpg"
  },
  {
    "code": "SAR015AC",
    "original_codes": [
      "2816870800"
    ],
    "description": "SHOCK ABSORBER 85N SHORT - ARCELIK - BEKO 281687080085N, holes: Ø11+11mm. Lenght: min 190, max  287mm.",
    "image_url": "http://omniacomponents.s3.eu-west-1.amazonaws.com/images/lambdaresized/500x500/LAVAGGIO/31_Ammortizzatori-balestre/SAR015AC.jpg"
  },
  {
    "code": "SAR012ZN",
    "original_codes": [
      "132255301"
    ],
    "description": "SHOCK ABSORBER 80N LONG - ZANUSSI 132255301Long, 80N, holes:  Ø10+10mm.",
    "image_url": "http://omniacomponents.s3.eu-west-1.amazonaws.com/images/lambdaresized/500x500/LAVAGGIO/31_Ammortizzatori-balestre/SAR012ZN.jpg"
  },
  {
    "code": "SAR012AC",
    "original_codes": [
      "2810430100",
      "2816870400",
      "2816870800"
    ],
    "description": "SHOCK ABSORBER 85N LONG - ARCELIK - BEKO 281687040085N, holes: Ø11+11mm, lenght: 270-310mm.",
    "image_url": "http://omniacomponents.s3.eu-west-1.amazonaws.com/images/lambdaresized/500x500/LAVAGGIO/31_Ammortizzatori-balestre/SAR012AC.jpg"
  },
  {
    "code": "SAR000VE",
    "original_codes": [
      "47001197",
      "49017455"
    ],
    "description": "SHOCK ABSORBER 80N LONG - VESTEL 47001197-49017455Holes: Ø10+10mm, 80N, lenght: min 180, max 278 mm.  Long.",
    "image_url": "http://omniacomponents.s3.eu-west-1.amazonaws.com/images/lambdaresized/500x500/LAVAGGIO/31_Ammortizzatori-balestre/SAR000VE.jpg"
  },
  {
    "code": "SAR002LG",
    "original_codes": [
      "4901ER2003B"
    ],
    "description": "SHOCK ABSORBER 80N - LG 4901ER2003B80N, holes:  Ø11+11mm.",
    "image_url": "http://omniacomponents.s3.eu-west-1.amazonaws.com/images/lambdaresized/500x500/LAVAGGIO/31_Ammortizzatori-balestre/SAR002LG.jpg"
  },
  {
    "code": "SAR025AC",
    "original_codes": [
      "2810430100"
    ],
    "description": "SHOCK ABSORBER - ARCELIK 90N 2810430100 - CIMA90N. Holes: Ø11+11mm. Fixing holes:  165/265mm",
    "image_url": "http://omniacomponents.s3.eu-west-1.amazonaws.com/images/lambdaresized/500x500/LAVAGGIO/31_Ammortizzatori-balestre/SAR025AC.jpg"
  },
  {
    "code": "SAR018AC",
    "original_codes": [
      "2816871100"
    ],
    "description": "SHOCK ABSORBER 110N - ARCELIK - BEKO 2816871100110N, holes:  Ø11+11mm.",
    "image_url": "http://omniacomponents.s3.eu-west-1.amazonaws.com/images/lambdaresized/500x500/LAVAGGIO/31_Ammortizzatori-balestre/SAR018AC.jpg"
  },
  {
    "code": "SAR021ZN",
    "original_codes": [
      "1322553601",
      "1322553700",
      "1327440002",
      "1327440028"
    ],
    "description": "SHOCK ABSORBER 60N - ZANUSSI 132255360160N. Length: max. 215mm, min. 153mm. Holes:  Ø11+11mm.",
    "image_url": "http://omniacomponents.s3.eu-west-1.amazonaws.com/images/lambdaresized/500x500/LAVAGGIO/31_Ammortizzatori-balestre/SAR021ZN.jpg"
  },
  {
    "code": "SAR001LG",
    "original_codes": [
      "4901ER2003A"
    ],
    "description": "SHOCK ABSORBER 100N - LG 4901ER2003AHoles: Ø11mm+11mm. Length: max 280, min 190mm.  100N.",
    "image_url": "http://omniacomponents.s3.eu-west-1.amazonaws.com/images/lambdaresized/500x500/LAVAGGIO/31_Ammortizzatori-balestre/SAR001LG.jpg"
  },
  {
    "code": "SAR008SA",
    "original_codes": [
      "DC66-00343K"
    ],
    "description": "SHOCK ABSORBER 60N - SAMSUNG DC66-00343K60N, holes:  Ø10+13mm.",
    "image_url": "http://omniacomponents.s3.eu-west-1.amazonaws.com/images/lambdaresized/500x500/LAVAGGIO/31_Ammortizzatori-balestre/SAR008SA.jpg"
  },
  {
    "code": "SAR003LG",
    "original_codes": [
      "4900FR2030D",
      "4900FR2030H",
      "4900FR2030J",
      "4901ER2001C"
    ],
    "description": "SHOCK ABSORBER 100N - LG 4900FR2030H - SUSPA100N, holes: Ø11+11mm. Length: min. 180mm, max.  278mm.",
    "image_url": "http://omniacomponents.s3.eu-west-1.amazonaws.com/images/lambdaresized/500x500/LAVAGGIO/31_Ammortizzatori-balestre/SAR003LG.jpg"
  },
  {
    "code": "SAR001MI",
    "original_codes": [
      "00118869",
      "04151285",
      "04500820",
      "04500823",
      "04500826",
      "06200778",
      "118869",
      "4500826"
    ],
    "description": "SHOCK ABSORBER 120N - BOSCH - MIELE  04151285120N, holes: Ø8+8mm. Fixing holes: 190/275mm.\u0026#x20;",
    "image_url": "http://omniacomponents.s3.eu-west-1.amazonaws.com/images/lambdaresized/500x500/LAVAGGIO/31_Ammortizzatori-balestre/SAR001MI.jpg"
  },
  {
    "code": "SAR005SA",
    "original_codes": [
      "DC66-00343F"
    ],
    "description": "SHOCK ABSORBER 60N - SAMSUNG DC66-00343F60N, holes: Ø10+10mm. Fixing holes: 170/260mm\u0026#x20;",
    "image_url": "http://omniacomponents.s3.eu-west-1.amazonaws.com/images/lambdaresized/500x500/LAVAGGIO/31_Ammortizzatori-balestre/SAR005SA.jpg"
  },
  {
    "code": "SAR007SA",
    "original_codes": [
      "DC66-00343J"
    ],
    "description": "SHOCK ABSORBER 80N - SAMSUNG DC66-00343J80N, holes:  Ø10+10mm.",
    "image_url": "http://omniacomponents.s3.eu-west-1.amazonaws.com/images/lambdaresized/500x500/LAVAGGIO/31_Ammortizzatori-balestre/SAR007SA.jpg"
  },
  {
    "code": "SAR003CY",
    "original_codes": [
      "46001947",
      "46001949",
      "81452780"
    ],
    "description": "SHOCK ABSORBER 100N LONG - CANDY 46001949100N, long. Length: max. 265mm, min. 185mm. Holes:  Ø11+13mm.",
    "image_url": "http://omniacomponents.s3.eu-west-1.amazonaws.com/images/lambdaresized/500x500/LAVAGGIO/31_Ammortizzatori-balestre/SAR003CY.jpg"
  },
  {
    "code": "SAR000SA",
    "original_codes": [
      "DC66-00531A"
    ],
    "description": "SHOCK ABSORBER 70N - SAMSUNG DC66-00531A70N, holes:  Ø12+10mm.",
    "image_url": "http://omniacomponents.s3.eu-west-1.amazonaws.com/images/lambdaresized/500x500/LAVAGGIO/31_Ammortizzatori-balestre/SAR000SA.jpg"
  },
  {
    "code": "SAR003SA",
    "original_codes": [
      "DC66-00343D"
    ],
    "description": "SHOCK ABSORBER 80N - SAMSUNG DC66-00343D80N, holes: Ø10+13mm. Fixing holes: Ø170+250mm\u0026#x20;",
    "image_url": "http://omniacomponents.s3.eu-west-1.amazonaws.com/images/lambdaresized/500x500/LAVAGGIO/31_Ammortizzatori-balestre/SAR003SA.jpg"
  },
  {
    "code": "SAR000AC",
    "original_codes": [
      "2001210200",
      "8996451471610"
    ],
    "description": "SHOCK ABSORBER 120N - ARCELIK-BEKO 2001210200120N, hole: Ø10mm. Length: min. 196mm, max.  270mm.",
    "image_url": "http://omniacomponents.s3.eu-west-1.amazonaws.com/images/lambdaresized/500x500/LAVAGGIO/31_Ammortizzatori-balestre/SAR000AC.jpg"
  },
  {
    "code": "SAR026ZN",
    "original_codes": [
      "1327442206"
    ],
    "description": "SHOCK ABSORBER - ZANUSSI 132744220690N. Length:  245mm.",
    "image_url": "http://omniacomponents.s3.eu-west-1.amazonaws.com/images/lambdaresized/500x500/LAVAGGIO/31_Ammortizzatori-balestre/SAR026ZN.jpg"
  },
  {
    "code": "SAR009WH",
    "original_codes": [
      "481246648088",
      "481252918038"
    ],
    "description": "SHOCK ABSORBER 120N - WHIRLPOOL 481246648088 - CIMA120N. Holes: Ø10+10mm. Length: min. 165mm, max.  260mm.",
    "image_url": "http://omniacomponents.s3.eu-west-1.amazonaws.com/images/lambdaresized/500x500/LAVAGGIO/31_Ammortizzatori-balestre/SAR009WH_3.jpg"
  },
  {
    "code": "SAR900SA",
    "original_codes": [
      "DC66-00626A"
    ],
    "description": "SHAFT FOR SHOCK ABSORBER SAR000AA SAMSUNG DC66-00626ALength:  155mm.",
    "image_url": "http://omniacomponents.s3.eu-west-1.amazonaws.com/images/lambdaresized/500x500/LAVAGGIO/31_Ammortizzatori-balestre/SAR900SA.jpg"
  },
  {
    "code": "SAR004SA",
    "original_codes": [
      "DC66-00343E"
    ],
    "description": "SHOCK ABSORBER 40N - SAMSUNG DC66-00343E40N, holes: Ø10+10mm. Lenght: 193mm -  297mm.",
    "image_url": "http://omniacomponents.s3.eu-west-1.amazonaws.com/images/lambdaresized/500x500/LAVAGGIO/31_Ammortizzatori-balestre/SAR004SA.jpg"
  },
  {
    "code": "SAR005ID",
    "original_codes": [
      "055039",
      "196002",
      "303587",
      "481246368035",
      "482000032251",
      "C00055039",
      "C00303587"
    ],
    "description": "SHOCK ABSORBER KIT 120N - INDESIT 303587 - CIMAHole Ø8mm - Ø13mm, length: min 185mm, max 295mm,  120N.",
    "image_url": "http://omniacomponents.s3.eu-west-1.amazonaws.com/images/lambdaresized/500x500/loghi_marchio/Indesit/INDESIT.jpg"
  },
  {
    "code": "SAR012SA",
    "original_codes": [
      "DC66-00343G"
    ],
    "description": "SHOCK ABSORBER 100N - SAMSUNG DC66-00343G - SUSPA100N, holes: Ø10+10mm. Length: min. 193mm, max.  300mm.",
    "image_url": "http://omniacomponents.s3.eu-west-1.amazonaws.com/images/lambdaresized/500x500/LAVAGGIO/31_Ammortizzatori-balestre/SAR012SA.jpg"
  },
  {
    "code": "SAR001WH",
    "original_codes": [
      "481246648088",
      "481252918038"
    ],
    "description": "GO TO SAR009WH120N. Holes: Ø10+10mm. Length: min. 165mm, max. 26 0mm.",
    "image_url": "http://omniacomponents.s3.eu-west-1.amazonaws.com/images/lambdaresized/500x500/LAVAGGIO/31_Ammortizzatori-balestre/SAR001WH.jpg"
  },
  {
    "code": "SAR000ID",
    "original_codes": [
      "055039"
    ],
    "description": "GO TO SAR005ID120N, holes: Ø13+8mm. Fixing holes: 180/270mm.",
    "image_url": "http://omniacomponents.s3.eu-west-1.amazonaws.com/images/lambdaresized/500x500/LAVAGGIO/31_Ammortizzatori-balestre/SAR000ID.jpg"
  },
  {
    "code": "SAR003GO",
    "original_codes": [
      "111818",
      "155262",
      "159737",
      "274404"
    ],
    "description": "SHOCK ABSORBER 120N - GORENJE 111818 - SUSPA120N. Length: max. 289mm, min. 184mm. Holes:  Ø12+8mm.",
    "image_url": "http://omniacomponents.s3.eu-west-1.amazonaws.com/images/lambdaresized/500x500/LAVAGGIO/31_Ammortizzatori-balestre/SAR003GO.jpg"
  },
  {
    "code": "SAR002SA",
    "original_codes": [
      "DC66-00531C"
    ],
    "description": "SHOCK ABSORBER 80N - SAMSUNG DC66-00531C80N, holes:  Ø10+13mm.",
    "image_url": "http://omniacomponents.s3.eu-west-1.amazonaws.com/images/lambdaresized/500x500/LAVAGGIO/31_Ammortizzatori-balestre/SAR002SA.jpg"
  },
  {
    "code": "SAR009SA",
    "original_codes": [
      "DC66-00343A"
    ],
    "description": "SHOCK ABSORBER 40N - SAMSUNG DC66-00343A40N. Holes: Ø10+10mm. Lenght: 296mm -  197mm.",
    "image_url": "http://omniacomponents.s3.eu-west-1.amazonaws.com/images/lambdaresized/500x500/LAVAGGIO/31_Ammortizzatori-balestre/SAR009SA.jpg"
  },
  {
    "code": "SAR000AD",
    "original_codes": [
      "039416",
      "499006400",
      "50015400",
      "651028066",
      "720128500"
    ],
    "description": "SHOCK ABSORBER 250N - ARDO 499006400 - 50015400250N, hole:  Ø10mm.",
    "image_url": "http://omniacomponents.s3.eu-west-1.amazonaws.com/images/lambdaresized/500x500/LAVAGGIO/31_Ammortizzatori-balestre/SAR000AD.jpg"
  },
  {
    "code": "SAR002MI",
    "original_codes": null,
    "description": "SHOCK ABSORBER 140N - MIELE - BOSCH140N. Holes: Ø8mm. Fixing holes: 190/275mm. Economic type.",
    "image_url": "http://omniacomponents.s3.eu-west-1.amazonaws.com/images/lambdaresized/500x500/LAVAGGIO/31_Ammortizzatori-balestre/SAR002MI.jpg"
  },
  {
    "code": "SAR013ZN",
    "original_codes": [
      "126063601"
    ],
    "description": "SHOCK ABSORBER 110N SHORT - ZANUSSI 126063601Short. 110N, holes:  Ø10+10mm.",
    "image_url": "http://omniacomponents.s3.eu-west-1.amazonaws.com/images/lambdaresized/500x500/LAVAGGIO/31_Ammortizzatori-balestre/SAR013ZN.jpg"
  },
  {
    "code": "SAR001IW",
    "original_codes": [
      "39201007700",
      "39901001200",
      "4055141297"
    ],
    "description": "SHOCK ABSORBER 80N - IT WASH 39201007700 - AKS80N. Holes: Ø13+Ø13mm. Length: min. 180mm,  max.272mm",
    "image_url": "http://omniacomponents.s3.eu-west-1.amazonaws.com/images/lambdaresized/500x500/LAVAGGIO/31_Ammortizzatori-balestre/SAR001IW.jpg"
  },
  {
    "code": "SAR003WH",
    "original_codes": [
      "461971421771",
      "480111102361"
    ],
    "description": "SHOCK ABSORBER - WHIRLPOOL 480111102361 - CIMA125N. Length: min. 165mm, max.  250mm.",
    "image_url": "http://omniacomponents.s3.eu-west-1.amazonaws.com/images/lambdaresized/500x500/LAVAGGIO/31_Ammortizzatori-balestre/SAR003WH.jpg"
  },
  {
    "code": "SAR015ZN",
    "original_codes": [
      "132255301",
      "41017168",
      "41017170",
      "41018714",
      "90488713"
    ],
    "description": "SHOCK ABSORBER 120N LONG - ZANUSSI -CANDY 41017168Long. 120N. Holes: Ø11+Ø11mm. Fixing holes: 183/26 8mm.",
    "image_url": "http://omniacomponents.s3.eu-west-1.amazonaws.com/images/lambdaresized/500x500/LAVAGGIO/31_Ammortizzatori-balestre/SAR015ZN.jpg"
  },
  {
    "code": "SAR006WH",
    "original_codes": [
      "481252918043",
      "481252918061"
    ],
    "description": "SHOCK ABSORBER 120N - WHIRLPOOL 481252918043 - CIMA120N. Hole: Ø10mm. Length: min. 165mm, max.  250mm.",
    "image_url": "http://omniacomponents.s3.eu-west-1.amazonaws.com/images/lambdaresized/500x500/LAVAGGIO/31_Ammortizzatori-balestre/SAR006WH.jpg"
  },
  {
    "code": "SAR010SA",
    "original_codes": [
      "DC66-00343C"
    ],
    "description": "SHOCK ABSORBER 60N - SAMSUNG DC66-00343C60N, holes: Ø10+10mm. Length max.254mm, min.  172mm.",
    "image_url": "http://omniacomponents.s3.eu-west-1.amazonaws.com/images/lambdaresized/500x500/LAVAGGIO/31_Ammortizzatori-balestre/SAR010SA.jpg"
  },
  {
    "code": "SAR027ZN",
    "original_codes": [
      "41017168",
      "49043541"
    ],
    "description": "SHOCK ABSORBER 120N LONG WITH SUPPORT - ZANUSSI-CANDY 41017168Long. 120N. Hole: Ø11mm. Fixing holes: 238mm.  With support.",
    "image_url": "http://omniacomponents.s3.eu-west-1.amazonaws.com/images/lambdaresized/500x500/LAVAGGIO/31_Ammortizzatori-balestre/SAR027ZN.jpg"
  },
  {
    "code": "SAR010ZN",
    "original_codes": [
      "1326240015",
      "3794303010"
    ],
    "description": "SHOCK ABSORBER 80N - ZANUSSI 132624001580N, holes: Ø11+11mm. Thickness: 21mm. Length: min . 180mm, max. 260mm.",
    "image_url": "http://omniacomponents.s3.eu-west-1.amazonaws.com/images/lambdaresized/500x500/LAVAGGIO/31_Ammortizzatori-balestre/SAR010ZN.jpg"
  },
  {
    "code": "SAR014ZN",
    "original_codes": [
      "132255301 110N"
    ],
    "description": "SHOCK ABSORBER 110N LONG - ZANUSSI 132255301Long. 110N, holes:  Ø10+10mm.",
    "image_url": "http://omniacomponents.s3.eu-west-1.amazonaws.com/images/lambdaresized/500x500/LAVAGGIO/31_Ammortizzatori-balestre/SAR014ZN.jpg"
  },
  {
    "code": "SAR002AC",
    "original_codes": [
      "2001210100"
    ],
    "description": "SHOCK ABSORBER 100N - ARCELIK - BEKO 2001210100100N, holes:  Ø10+10mm.",
    "image_url": "http://omniacomponents.s3.eu-west-1.amazonaws.com/images/lambdaresized/500x500/LAVAGGIO/31_Ammortizzatori-balestre/SAR002AC.jpg"
  },
  {
    "code": "SAR005UN",
    "original_codes": null,
    "description": "WASHING MACHINE SHOCK ABSORBER 180N180N. Holes: Ø10+Ø10mm. Fixing holes:  188/288mm",
    "image_url": "http://omniacomponents.s3.eu-west-1.amazonaws.com/images/lambdaresized/500x500/LAVAGGIO/31_Ammortizzatori-balestre/SAR005UN.jpg"
  },
  {
    "code": "SAR009AC",
    "original_codes": [
      "2803250500"
    ],
    "description": "SHOCK ABSORBER 110N - ARCELIK - BEKO 2803250500110N, holes:  Ø11+11mm.",
    "image_url": "http://omniacomponents.s3.eu-west-1.amazonaws.com/images/lambdaresized/500x500/LAVAGGIO/31_Ammortizzatori-balestre/SAR009AC.jpg"
  },
  {
    "code": "SAR006ZN",
    "original_codes": [
      "4055211207",
      "8996453299507"
    ],
    "description": "SHOCK ABSORBER 100N - ZANUSSI 4055211207 - SUSPA100N,  holeØ10mm.",
    "image_url": "http://omniacomponents.s3.eu-west-1.amazonaws.com/images/lambdaresized/500x500/LAVAGGIO/31_Ammortizzatori-balestre/SAR006ZN.jpg"
  },
  {
    "code": "SAR003ID",
    "original_codes": [
      "140744",
      "482000023502",
      "C00140670",
      "C00140744",
      "C00309597"
    ],
    "description": "SHOCK ABSORBER 100N - INDESIT 140744 - SUSPA100N, hole: Ø13mm, fixing holes:  164/225mm.",
    "image_url": "http://omniacomponents.s3.eu-west-1.amazonaws.com/images/lambdaresized/500x500/LAVAGGIO/31_Ammortizzatori-balestre/SAR003ID.jpg"
  },
  {
    "code": "SAR017ZN",
    "original_codes": [
      "1108429000",
      "1108429001",
      "4071361465"
    ],
    "description": "SHOCK ABSORBER 80N - ZANUSSI 4071361465 - SUSPA80N. Holes: Ø12+12mm. Fixing holes:  175/270mm.",
    "image_url": "http://omniacomponents.s3.eu-west-1.amazonaws.com/images/lambdaresized/500x500/LAVAGGIO/31_Ammortizzatori-balestre/SAR017ZN.jpg"
  },
  {
    "code": "SAR003VE",
    "original_codes": [
      "47005034"
    ],
    "description": "SHOCK ABSORBER 120N - VESTEL 47005034120N, holes:  Ø11+11mm.",
    "image_url": "http://omniacomponents.s3.eu-west-1.amazonaws.com/images/lambdaresized/500x500/LAVAGGIO/31_Ammortizzatori-balestre/SAR003VE.jpg"
  },
  {
    "code": "SAR007AC",
    "original_codes": [
      "2803250200"
    ],
    "description": "SHOCK ABSORBER 85N - ARCELIK - BEKO 280325020085N, holes:  Ø10+11mm.",
    "image_url": "http://omniacomponents.s3.eu-west-1.amazonaws.com/images/lambdaresized/500x500/LAVAGGIO/31_Ammortizzatori-balestre/SAR007AC.jpg"
  },
  {
    "code": "SAR010WH",
    "original_codes": [
      "313195",
      "461971408981",
      "461975277441",
      "481252918062",
      "481252918063"
    ],
    "description": "SHOCK ABSORBER 120N - WHIRLPOOL 481252918063 - CIMA120N. Holes: Ø10+8mm. Length: min. 165mm, max.  263mm. With bracket.",
    "image_url": "http://omniacomponents.s3.eu-west-1.amazonaws.com/images/lambdaresized/500x500/LAVAGGIO/31_Ammortizzatori-balestre/SAR010WH.jpg"
  },
  {
    "code": "SAR001PH",
    "original_codes": [
      "050563"
    ],
    "description": "SHOCK ABSORBER SHORT 150N 477 - PHILCO 050563150N. Shock absorber left short  type.",
    "image_url": "http://omniacomponents.s3.eu-west-1.amazonaws.com/images/lambdaresized/500x500/LAVAGGIO/31_Ammortizzatori-balestre/SAR001PH.jpg"
  },
  {
    "code": "SAR007WH",
    "original_codes": [
      "313195",
      "461971408981",
      "461975277441",
      "481252918062",
      "481252918063"
    ],
    "description": "SHOCK ABSORBER 120N - WHIRLPOOL 481252918063 - SUSPA120N. Holes: Ø10+9mm. Length: min. 165mm, max.  263mm. With bracket.",
    "image_url": "http://omniacomponents.s3.eu-west-1.amazonaws.com/images/lambdaresized/500x500/LAVAGGIO/31_Ammortizzatori-balestre/SAR007WH.jpg"
  },
  {
    "code": "SAR000PH",
    "original_codes": [
      "050560"
    ],
    "description": "SHOCK ABSORBER LONG 120N 478 - PHILCO 050560120N. Long on right side. Fixing holes:  195+285mm.Holes: Ø10+10mm",
    "image_url": "http://omniacomponents.s3.eu-west-1.amazonaws.com/images/lambdaresized/500x500/LAVAGGIO/31_Ammortizzatori-balestre/SAR000PH.jpg"
  },
  {
    "code": "SAR004VE",
    "original_codes": [
      "47010522"
    ],
    "description": "SHOCK ABSORBER 80N - VESTEL 47010522 - AKS80N. Holes: Ø11+Ø11mm. Length: min. 170mm, max.  270mm.",
    "image_url": "http://omniacomponents.s3.eu-west-1.amazonaws.com/images/lambdaresized/500x500/LAVAGGIO/31_Ammortizzatori-balestre/SAR004VE.jpg"
  },
  {
    "code": "SAR004AC",
    "original_codes": [
      "2001210400"
    ],
    "description": "SHOCK ABSORBER 85N - ARCELIK - BEKO 200121040085 N, hole:  Ø11-11mm.",
    "image_url": "http://omniacomponents.s3.eu-west-1.amazonaws.com/images/lambdaresized/500x500/LAVAGGIO/31_Ammortizzatori-balestre/SAR004AC.jpg"
  },
  {
    "code": "SAR002WH",
    "original_codes": [
      "00311556",
      "46197141545",
      "461971415451",
      "480111100195",
      "C00311556"
    ],
    "description": "SHOCK ABSORBER - WHIRLPOOL 480111100195 - SUSPA120N. Fixing holes: min. 165mm, max. 260mm. RD 18S .",
    "image_url": "http://omniacomponents.s3.eu-west-1.amazonaws.com/images/lambdaresized/500x500/LAVAGGIO/31_Ammortizzatori-balestre/SAR002WH.jpg"
  },
  {
    "code": "SAR006AC",
    "original_codes": [
      "2803250100"
    ],
    "description": "SHOCK ABSORBER 85N - ARCELIK - BEKO 280325010085N, holes:  Ø11+11mm.",
    "image_url": "http://omniacomponents.s3.eu-west-1.amazonaws.com/images/lambdaresized/500x500/LAVAGGIO/31_Ammortizzatori-balestre/SAR006AC.jpg"
  },
  {
    "code": "SAR001SA",
    "original_codes": [
      "DC66-00531B"
    ],
    "description": "SHOCK ABSORBER 40N - SAMSUNG DC66-00531B40N.",
    "image_url": "http://omniacomponents.s3.eu-west-1.amazonaws.com/images/lambdaresized/500x500/LAVAGGIO/31_Ammortizzatori-balestre/SAR001SA.jpg"
  },
  {
    "code": "SAR008WH",
    "original_codes": [
      "461971408981",
      "461975277441",
      "481252918062",
      "481252918063"
    ],
    "description": "SHOCK ABSORBER 120N - WHIRLPOOL 481252918063 - AKS120N. With bracket. Holes: Ø10+8mm. Lenght: min.  165mm, max. 267mm.",
    "image_url": "http://omniacomponents.s3.eu-west-1.amazonaws.com/images/lambdaresized/500x500/LAVAGGIO/31_Ammortizzatori-balestre/SAR008WH.jpg"
  },
  {
    "code": "SAR010AC",
    "original_codes": [
      "2816870100"
    ],
    "description": "SHOCK ABSORBER 110N - ARCELIK - BEKO 2816870100110N, holes:  Ø11+11mm.",
    "image_url": "http://omniacomponents.s3.eu-west-1.amazonaws.com/images/lambdaresized/500x500/LAVAGGIO/31_Ammortizzatori-balestre/SAR010AC.jpg"
  },
  {
    "code": "SAR011SA",
    "original_codes": [
      "DC66-00421A"
    ],
    "description": "SHOCK ABSORBER 80N - SAMSUNG DC66-00421AN80. Holes: Ø10+10mm. Lenght: min. 167mm, max.  265mm.",
    "image_url": "http://omniacomponents.s3.eu-west-1.amazonaws.com/images/lambdaresized/500x500/LAVAGGIO/31_Ammortizzatori-balestre/SAR011SA.jpg"
  },
  {
    "code": "SAR014AC",
    "original_codes": [
      "2816870700"
    ],
    "description": "SHOCK ABSORBER 85N - ARCELIK - BEKO 281687070085N, holes:  Ø10+11mm.",
    "image_url": "http://omniacomponents.s3.eu-west-1.amazonaws.com/images/lambdaresized/500x500/LAVAGGIO/31_Ammortizzatori-balestre/SAR014AC.jpg"
  },
  {
    "code": "SAR004LG",
    "original_codes": [
      "ACV72909503"
    ],
    "description": "SHOCK ABSORBER 80N - LG ACV72909503 - AKS80N. Holes: Ø11+Ø11mm. Length: min. 170mm,  max.265mm.",
    "image_url": "http://omniacomponents.s3.eu-west-1.amazonaws.com/images/lambdaresized/500x500/LAVAGGIO/31_Ammortizzatori-balestre/SAR004LG.jpg"
  },
  {
    "code": "SAR000IW",
    "original_codes": [
      "39201016100"
    ],
    "description": "SHOCK ABSORBER 100N - IT WASH 39201016100 - AKS100N. Holes: Ø13+Ø13mm. Length: min. 190mm,  max.280mm",
    "image_url": "http://omniacomponents.s3.eu-west-1.amazonaws.com/images/lambdaresized/500x500/LAVAGGIO/31_Ammortizzatori-balestre/SAR000IW.jpg"
  },
  {
    "code": "SAR000MI",
    "original_codes": [
      "00118869",
      "04151285",
      "04500820",
      "04500823",
      "04500826",
      "06200778",
      "118869",
      "4500826"
    ],
    "description": "SHOCK ABSORBER 120N - MIELE 04151285 - SUSPA120N, RD 12. With hole Ø8mm. Length: min. 175mm, m ax. 247mm. Friction power tolerance: ±30N.",
    "image_url": "http://omniacomponents.s3.eu-west-1.amazonaws.com/images/lambdaresized/500x500/LAVAGGIO/31_Ammortizzatori-balestre/SAR000MI.jpg"
  },
  {
    "code": "SAR005VE",
    "original_codes": [
      "47011586",
      "49032200",
      "M6547011586"
    ],
    "description": "SHOCK ABSORBER 80N - VESTEL 47011586 - AKS80N. Holes: Ø11+Ø11mm. Length: min. 166mm,  max.258mm",
    "image_url": "http://omniacomponents.s3.eu-west-1.amazonaws.com/images/lambdaresized/500x500/LAVAGGIO/31_Ammortizzatori-balestre/SAR005VE.jpg"
  },
  {
    "code": "SAR001CY",
    "original_codes": null,
    "description": "FRICTION PAD - CANDY 91941756 - ORIGINAL",
    "image_url": "http://omniacomponents.s3.eu-west-1.amazonaws.com/images/lambdaresized/500x500/LAVAGGIO/31_Ammortizzatori-balestre/SAR001CY.jpg"
  },
  {
    "code": "SAR020AC",
    "original_codes": [
      "2816871400"
    ],
    "description": "SHOCK ABSORBER 110N - ARCELIK - BEKO 2816871400110N, holes:  Ø11+11mm.",
    "image_url": "http://omniacomponents.s3.eu-west-1.amazonaws.com/images/lambdaresized/500x500/LAVAGGIO/31_Ammortizzatori-balestre/SAR020AC.jpg"
  },
  {
    "code": "SAR021AC",
    "original_codes": [
      "2816871500"
    ],
    "description": "SHOCK ABSORBER 110N - ARCELIK - BEKO 2816871500110N, holes:  Ø11+11mm.",
    "image_url": "http://omniacomponents.s3.eu-west-1.amazonaws.com/images/lambdaresized/500x500/LAVAGGIO/31_Ammortizzatori-balestre/SAR021AC.jpg"
  },
  {
    "code": "SAR023AC",
    "original_codes": [
      "2829010100"
    ],
    "description": "SHOCK ABSORBER 85N - ARCELIK - BEKO 282901010085N, holes:  Ø11+8mm.",
    "image_url": "http://omniacomponents.s3.eu-west-1.amazonaws.com/images/lambdaresized/500x500/LAVAGGIO/31_Ammortizzatori-balestre/SAR023AC.jpg"
  },
  {
    "code": "SAR008AC",
    "original_codes": [
      "2803250300"
    ],
    "description": "SHOCK ABSORBER 110N - ARCELIK - BEKO 2803250300110N, holes:  Ø11+10mm.",
    "image_url": "http://omniacomponents.s3.eu-west-1.amazonaws.com/images/lambdaresized/500x500/LAVAGGIO/31_Ammortizzatori-balestre/SAR008AC.jpg"
  },
  {
    "code": "SAR000GO",
    "original_codes": [
      "391857",
      "393121",
      "634801"
    ],
    "description": "SHOCK ABSORBER - GORENJE 391857 - 634801 - SUSPA",
    "image_url": "http://omniacomponents.s3.eu-west-1.amazonaws.com/images/lambdaresized/500x500/LAVAGGIO/31_Ammortizzatori-balestre/SAR000GO.jpg"
  },
  {
    "code": "SAR000AE",
    "original_codes": [
      "8996451471610"
    ],
    "description": "SHOCK ABSORBER 120N - AEG 8996451471610 - SUSPA120N, hole: Ø10mm. Length: min. 185mm, max.  280mm.",
    "image_url": "http://omniacomponents.s3.eu-west-1.amazonaws.com/images/lambdaresized/500x500/LAVAGGIO/31_Ammortizzatori-balestre/SAR000AE.jpg"
  },
  {
    "code": "SAR001ID",
    "original_codes": [
      "055039",
      "196002",
      "303587",
      "481246368035",
      "482000032251",
      "C00055039",
      "C00303587"
    ],
    "description": "SHOCK ABSORBER KIT 2 pcs 120N - INDESIT 303587 - CIMAHole Ø8mm - Ø13mm, length: min 185mm, max 295mm,  120N.",
    "image_url": "http://omniacomponents.s3.eu-west-1.amazonaws.com/images/lambdaresized/500x500/LAVAGGIO/31_Ammortizzatori-balestre/SAR001ID.jpg"
  },
  {
    "code": "2816870800",
    "original_codes": [
      "2816870800"
    ],
    "description": "SHOCK ABSORBER BEKO 2816870800 - ORIGINAL85N, holes: Ø11+11mm. Lenght: 190-287mm.",
    "image_url": "http://omniacomponents.s3.eu-west-1.amazonaws.com/images/lambdaresized/500x500/loghi_marchio/Arcelik/arcelik-beko.jpg"
  },
  {
    "code": "SAR002GO",
    "original_codes": [
      "391856",
      "393120",
      "634802"
    ],
    "description": "SHOCK ABSORBER - GORENJE 391856 - 634802 - SUSPAMax length 370mm. Suspension rod lenght:  180mm",
    "image_url": "http://omniacomponents.s3.eu-west-1.amazonaws.com/images/lambdaresized/500x500/LAVAGGIO/31_Ammortizzatori-balestre/SAR002GO.jpg"
  },
  {
    "code": "SAR004BO",
    "original_codes": [
      "188222",
      "433761",
      "448032"
    ],
    "description": "SHOCK ABSORBER 90N KIT 2pcs - BOSCH 448032 Kit 2pcs. 90N. Holes: Ø11+8mm. Length: min 165mm,  max 265mm.",
    "image_url": "http://omniacomponents.s3.eu-west-1.amazonaws.com/images/lambdaresized/500x500/LAVAGGIO/31_Ammortizzatori-balestre/SAR004BO.jpg"
  },
  {
    "code": "SAR008BO",
    "original_codes": [
      "660865",
      "673541",
      "742719",
      "9000446302"
    ],
    "description": "SHOCK ABSORBER 80N - BOSCH 742719 - SUSPAN80, holes: Ø8+Ø14mm. Fixing holes:  165/255mm.",
    "image_url": "http://omniacomponents.s3.eu-west-1.amazonaws.com/images/lambdaresized/500x500/LAVAGGIO/31_Ammortizzatori-balestre/SAR008BO.jpg"
  },
  {
    "code": "SAR017AC",
    "original_codes": [
      "2816871000"
    ],
    "description": "SHOCK ABSORBER 85N - ARCELIK - BEKO 281687100085N, holes:  Ø11+11mm.",
    "image_url": "http://omniacomponents.s3.eu-west-1.amazonaws.com/images/lambdaresized/500x500/LAVAGGIO/31_Ammortizzatori-balestre/SAR017AC.jpg"
  },
  {
    "code": "SAR019AC",
    "original_codes": [
      "2816871200"
    ],
    "description": "SHOCK ABSORBER 85N - ARCELIK - BEKO 281687120085N, holes:  Ø11+11mm.",
    "image_url": "http://omniacomponents.s3.eu-west-1.amazonaws.com/images/lambdaresized/500x500/LAVAGGIO/31_Ammortizzatori-balestre/SAR019AC.jpg"
  },
  {
    "code": "SAR005BO",
    "original_codes": [
      "118869"
    ],
    "description": "SHOCK ABSORBER 90N KIT 2pcs - BOSCH 118869Kit 2pcs. 90N. Holes: Ø8+8mm. Length: min 215mm,  max 307mm.",
    "image_url": "http://omniacomponents.s3.eu-west-1.amazonaws.com/images/lambdaresized/500x500/LAVAGGIO/31_Ammortizzatori-balestre/SAR005BO.jpg"
  },
  {
    "code": "2816871100",
    "original_codes": [
      "2816871100"
    ],
    "description": "SHOCK ABSORBER - BEKO - ORIGINAL",
    "image_url": "http://omniacomponents.s3.eu-west-1.amazonaws.com/images/lambdaresized/500x500/loghi_marchio/Arcelik/arcelik-beko.jpg"
  },
  {
    "code": "SAR001GO",
    "original_codes": [
      "360457",
      "392817",
      "393119",
      "607725299"
    ],
    "description": "SHOCK ABSORBER 88N - GORENJE 392817 - 393119 - SUSPA88N. Length:  160mm.",
    "image_url": "http://omniacomponents.s3.eu-west-1.amazonaws.com/images/lambdaresized/500x500/LAVAGGIO/31_Ammortizzatori-balestre/SAR001GO.jpg"
  },
  {
    "code": "SAR022AC",
    "original_codes": [
      "2810430100"
    ],
    "description": "SHOCK ABSORBER 85N - ARCELIK-BEKO 2810430100 - ORIGINAL85N. Length: min. 183mm, max. 280mm. Holes: Ø11+11 mm.",
    "image_url": "http://omniacomponents.s3.eu-west-1.amazonaws.com/images/lambdaresized/500x500/LAVAGGIO/31_Ammortizzatori-balestre/SAR022AC.jpg"
  },
  {
    "code": "SAR009MI",
    "original_codes": [
      "00118869",
      "04151285",
      "04500820",
      "04500823",
      "04500826",
      "06200778",
      "118869",
      "4500826"
    ],
    "description": "SHOCK ABSORBER 120N - MIELE 04151285 - SUSPA120N, RD 12. With hole Ø8mm. Length: min. 175mm,  max. 247mm. Friction power tolerance: ±20N.",
    "image_url": "http://omniacomponents.s3.eu-west-1.amazonaws.com/images/lambdaresized/500x500/loghi_marchio/Miele/MIELE.jpg"
  },
  {
    "code": "SAR900UN",
    "original_codes": null,
    "description": "SHOCK ABSORBER REPAIR KIT FOR AWEKO 80-110N 2pcsSuspension repair set 2pcs for SAR003BO and shock  absorber Aweko type 80N-100N.",
    "image_url": "http://omniacomponents.s3.eu-west-1.amazonaws.com/images/lambdaresized/500x500/LAVAGGIO/31_Ammortizzatori-balestre/SAR900UN.jpg"
  },
  {
    "code": "SAR005AC",
    "original_codes": [
      "2200280000"
    ],
    "description": "SHOCK ABSORBER - ARCELIK - BEKO 2200280000-107653Lenght: 330mm",
    "image_url": "http://omniacomponents.s3.eu-west-1.amazonaws.com/images/lambdaresized/500x500/LAVAGGIO/31_Ammortizzatori-balestre/SAR005AC.jpg"
  },
  {
    "code": "SAR013SA",
    "original_codes": [
      "DC66-00470A"
    ],
    "description": "SHOCK ABSORBER 80N - SAMSUNG DC66-00470A - SUSPA80N. fixing holes: 165/260mm, holes: Ø10/10mm. RD  18 FL.",
    "image_url": "http://omniacomponents.s3.eu-west-1.amazonaws.com/images/lambdaresized/500x500/LAVAGGIO/31_Ammortizzatori-balestre/SAR013SA.jpg"
  },
  {
    "code": "SAR003BO",
    "original_codes": [
      "00742719",
      "660865",
      "673541",
      "742719"
    ],
    "description": "SHOCK ABSORBER N90 KIT 2pcs - BOSCH 673541 Kit 2pcs. N90, holes: Ø8+13mm. Fixing holes: 173/255mm.",
    "image_url": "http://omniacomponents.s3.eu-west-1.amazonaws.com/images/lambdaresized/500x500/LAVAGGIO/31_Ammortizzatori-balestre/SAR003BO.jpg"
  },
  {
    "code": "SAR009ZN",
    "original_codes": [
      "4055211207",
      "8996453299507"
    ],
    "description": "AMMORTIZZATORE ZANUSSI 100N 4055211207 Shock absorber. 100N, hole Ø10mm.",
    "image_url": "http://omniacomponents.s3.eu-west-1.amazonaws.com/images/lambdaresized/500x500/LAVAGGIO/31_Ammortizzatori-balestre/SAR006ZN.jpg"
  },
  {
    "code": "41009196",
    "original_codes": [
      "41009196"
    ],
    "description": "SHOCK ABSORBER 41009196",
    "image_url": "http://omniacomponents.s3.eu-west-1.amazonaws.com/images/lambdaresized/500x500/loghi_marchio/Candy/Candy_logo.jpg"
  },
  {
    "code": "SAR008ZN",
    "original_codes": [
      "4055211207",
      "8996450506309",
      "8996451209606",
      "8996453289507"
    ],
    "description": "SCHOCK ABSORBER 100N KIT 2pcs - ZANUSSI 8996453289507Kit 2pcs. 100N. Length: max. 270mm, min. 185mm.  Holes: Ø10+Ø10mm.",
    "image_url": "http://omniacomponents.s3.eu-west-1.amazonaws.com/images/lambdaresized/500x500/LAVAGGIO/31_Ammortizzatori-balestre/SAR008ZN.jpg"
  },
  {
    "code": "SAR000AA",
    "original_codes": [
      "8029508",
      "DC66-00627A"
    ],
    "description": "SHOCK ABSORBER 55N - AMICA 8029508 - DC66-00627ALength: 235mm, 55N.",
    "image_url": "http://omniacomponents.s3.eu-west-1.amazonaws.com/images/lambdaresized/500x500/LAVAGGIO/31_Ammortizzatori-balestre/SAR000AA.jpg"
  },
  {
    "code": "SAR003MI",
    "original_codes": [
      "04151285",
      "04500823",
      "04500826",
      "06200778"
    ],
    "description": "SHOCK ABSORBER 120N KIT 2pcs - MIELE 04151285 - SUSPA120N, with hole Ø8mm. Length: min. 175mm, max. 247 mm.",
    "image_url": "http://omniacomponents.s3.eu-west-1.amazonaws.com/images/lambdaresized/500x500/LAVAGGIO/31_Ammortizzatori-balestre/SAR003MI.jpg"
  },
  {
    "code": "634801",
    "original_codes": [
      "608998",
      "634801"
    ],
    "description": "SHOCK ABSORBER GORENJE",
    "image_url": "http://omniacomponents.s3.eu-west-1.amazonaws.com/images/lambdaresized/500x500/loghi_marchio/Gorenje/GORENJE.jpg"
  },
  {
    "code": "SAR001AA",
    "original_codes": [
      "8010343",
      "8029504",
      "DC66-00628A"
    ],
    "description": "SHOCK ABSORBER 80N - AMICA 8029504 - DC66-00628A80N. Length: 230mm",
    "image_url": "http://omniacomponents.s3.eu-west-1.amazonaws.com/images/lambdaresized/500x500/LAVAGGIO/31_Ammortizzatori-balestre/SAR001AA.jpg"
  },
  {
    "code": "SAR001AC",
    "original_codes": [
      "2952010100"
    ],
    "description": "TUMBLE DRYER DRUM BEARING PAD KIT 4pcs - BEKO 2952010100Kit 4pcs.",
    "image_url": "http://omniacomponents.s3.eu-west-1.amazonaws.com/images/lambdaresized/500x500/LAVAGGIO/31_Ammortizzatori-balestre/SAR001AC.jpg"
  },
  {
    "code": "480110100803",
    "original_codes": [
      "481252918052"
    ],
    "description": "SHOCK ABSORBER WHIRLPOOL",
    "image_url": "http://omniacomponents.s3.eu-west-1.amazonaws.com/images/lambdaresized/500x500/ORIGINALI/480110100803.jpg"
  },
  {
    "code": "SAR002BO",
    "original_codes": [
      "188222",
      "433761",
      "448032"
    ],
    "description": "SHOCK ABSORBER 90N - BOSCH 448032 - SUSPAHole Ø13mm. Length: min 180mm, max 245mm,  90N.",
    "image_url": "http://omniacomponents.s3.eu-west-1.amazonaws.com/images/lambdaresized/500x500/LAVAGGIO/31_Ammortizzatori-balestre/SAR002BO.jpg"
  },
  {
    "code": "SAR007BO",
    "original_codes": [
      "00742719",
      "660865",
      "673541",
      "9000446302"
    ],
    "description": "SHOCK ABSORBER N90 - BOSCH 742719 KIT 2pcs - SUSPAN80, holes: Ø8+Ø13mm. Fixing holes: 165/255mm. Kit  2 pcs.",
    "image_url": "http://omniacomponents.s3.eu-west-1.amazonaws.com/images/lambdaresized/500x500/LAVAGGIO/31_Ammortizzatori-balestre/SAR007BO.jpg"
  },
  {
    "code": "SAR006MI",
    "original_codes": [
      "10555950"
    ],
    "description": "SHOCK ABSORBER 75N - MIELE 10555950 - AKS75N. Holes: Ø9+Ø11mm. Length: min. 175mm,  max.275mm. With bracket.",
    "image_url": "http://omniacomponents.s3.eu-west-1.amazonaws.com/images/lambdaresized/500x500/LAVAGGIO/31_Ammortizzatori-balestre/SAR006MI.jpg"
  },
  {
    "code": "SAR007MI",
    "original_codes": [
      "10555580"
    ],
    "description": "SHOCK ABSORBER 120N - MIELE 10555580 - AKS120N. Holes: Ø9+Ø11mm. Length: min. 173mm,  max.273mm. With bracket.",
    "image_url": "http://omniacomponents.s3.eu-west-1.amazonaws.com/images/lambdaresized/500x500/LAVAGGIO/31_Ammortizzatori-balestre/SAR007MI.jpg"
  },
  {
    "code": "SAR005MI",
    "original_codes": [
      "10084090"
    ],
    "description": "SHOCK ABSORBER 120N - MIELE 10084090 - AKS120N. Holes: Ø8+Ø9mm.  Length: min. 172mm,  max.270mm. With bracket.",
    "image_url": "http://omniacomponents.s3.eu-west-1.amazonaws.com/images/lambdaresized/500x500/LAVAGGIO/31_Ammortizzatori-balestre/SAR005MI.jpg"
  },
  {
    "code": "SAR004MI",
    "original_codes": [
      "10084080"
    ],
    "description": "SHOCK ABSORBER 75N - MIELE 10084080 - AKS75N. Holes: Ø8+Ø10mm. Length: min. 174mm,  max.264mm. With bracket.",
    "image_url": "http://omniacomponents.s3.eu-west-1.amazonaws.com/images/lambdaresized/500x500/LAVAGGIO/31_Ammortizzatori-balestre/SAR004MI.jpg"
  },
  {
    "code": "SAR008MI",
    "original_codes": [
      "10095440"
    ],
    "description": "SHOCK ABSORBER 75N - MIELE 10095440 - SUSPA75N, RD  18.",
    "image_url": "http://omniacomponents.s3.eu-west-1.amazonaws.com/images/lambdaresized/500x500/loghi_marchio/Miele/MIELE.jpg"
  },
  {
    "code": "SAR000HP",
    "original_codes": [
      "1600429",
      "C00197934"
    ],
    "description": "SHOCK ABSORBER - HOTPOINT 1600429 - AKSMax length 345mm. Suspension rod lenght:  150mm",
    "image_url": "http://omniacomponents.s3.eu-west-1.amazonaws.com/images/lambdaresized/500x500/LAVAGGIO/31_Ammortizzatori-balestre/SAR000HP.jpg"
  },
  {
    "code": "651013992",
    "original_codes": [
      "651013992"
    ],
    "description": "SHOCK ABSORBER ARDO",
    "image_url": "http://omniacomponents.s3.eu-west-1.amazonaws.com/images/lambdaresized/500x500/loghi_marchio/Ardo/Ardo.png"
  },
  {
    "code": "SAR000LG",
    "original_codes": [
      "4900FR2030H",
      "4901ER2001C"
    ],
    "description": "SHOCK ABSORBER 100N - LG 4900FR2030H - ORIGINAL100N, holes: Ø11+11mm. Length: min. 180mm, max.  278mm.",
    "image_url": "http://omniacomponents.s3.eu-west-1.amazonaws.com/images/lambdaresized/500x500/LAVAGGIO/31_Ammortizzatori-balestre/SAR000LG.jpg"
  },
  {
    "code": "SAR012BO",
    "original_codes": [
      "660865",
      "673541",
      "742719"
    ],
    "description": "SHOCK ABSORBER 80N KIT 3pcs - BOSCH 742719Kit 3pcs. N80, holes: Ø8+Ø14mm. Fixing holes:  165/255mm. With accessories.",
    "image_url": "http://omniacomponents.s3.eu-west-1.amazonaws.com/images/lambdaresized/500x500/https://orbitvu.co/share/7fjQwjwDoRwe2YkYisw5TJ/3760267/360/view"
  },
  {
    "code": "480111102361",
    "original_codes": null,
    "description": "SHOCK ABSORBER WHIRLPOOL",
    "image_url": "http://omniacomponents.s3.eu-west-1.amazonaws.com/images/lambdaresized/500x500/loghi_marchio/Whirlpool/WHIRLPOOL.jpg"
  },
  {
    "code": "303582",
    "original_codes": [
      "303582",
      "C00303582"
    ],
    "description": "SHOCK ABSORBER KIT - INDESIT 303582",
    "image_url": "http://omniacomponents.s3.eu-west-1.amazonaws.com/images/lambdaresized/500x500/loghi_marchio/Whirlpool/WHIRLPOOL.jpg"
  },
  {
    "code": "309597",
    "original_codes": [
      "309597"
    ],
    "description": "WASHINGMACHINE SHOCK ABSORBER KIT-MERLONI",
    "image_url": "http://omniacomponents.s3.eu-west-1.amazonaws.com/images/lambdaresized/500x500/ORIGINALI/C00309597.jpg"
  },
  {
    "code": "481246648057",
    "original_codes": [
      "481246648057"
    ],
    "description": "SHOCK ABSORBER 100N -  WHIRLPOOL - ORIGINAL100N. Hole  8mm.",
    "image_url": "http://omniacomponents.s3.eu-west-1.amazonaws.com/images/lambdaresized/500x500/loghi_marchio/Whirlpool/WHIRLPOOL.jpg"
  },
  {
    "code": "481252918063",
    "original_codes": [
      "481252918063"
    ],
    "description": "SHOCK ABSORBER WHIRLPOOL",
    "image_url": "http://omniacomponents.s3.eu-west-1.amazonaws.com/images/lambdaresized/500x500/loghi_marchio/Whirlpool/WHIRLPOOL.jpg"
  },
  {
    "code": "481252918042",
    "original_codes": [
      "481252918042"
    ],
    "description": "SHOCK ABSORBER KIT - WHIRLPOOL 481252918042",
    "image_url": "http://omniacomponents.s3.eu-west-1.amazonaws.com/images/lambdaresized/500x500/loghi_marchio/Whirlpool/WHIRLPOOL.jpg"
  },
  {
    "code": "303583",
    "original_codes": [
      "093885",
      "C00303583"
    ],
    "description": "SHOCK ABSORBER INDESIT",
    "image_url": "http://omniacomponents.s3.eu-west-1.amazonaws.com/images/lambdaresized/500x500/loghi_marchio/Whirlpool/WHIRLPOOL.jpg"
  },
  {
    "code": "030340",
    "original_codes": [
      "482000026149",
      "C00030340"
    ],
    "description": "SHOCK ABSORBER MERLONI",
    "image_url": "http://omniacomponents.s3.eu-west-1.amazonaws.com/images/lambdaresized/500x500/loghi_marchio/Whirlpool/WHIRLPOOL.jpg"
  },
  {
    "code": "481246648088",
    "original_codes": [
      "481246648088",
      "481252918038"
    ],
    "description": "SHOCK ABSORBER 120N - WHIRLPOOL 481246648088 - ORIGINAL",
    "image_url": "http://omniacomponents.s3.eu-west-1.amazonaws.com/images/lambdaresized/500x500/LAVAGGIO/31_Ammortizzatori-balestre/SAR004WH.jpg"
  },
  {
    "code": "262816",
    "original_codes": [
      "119111",
      "C00262816"
    ],
    "description": "REPLACED BY C00290703",
    "image_url": "http://omniacomponents.s3.eu-west-1.amazonaws.com/images/lambdaresized/500x500/ORIGINALI/262816.jpg"
  },
  {
    "code": "481246368026",
    "original_codes": [
      "481246368026"
    ],
    "description": "SHOCK ABSORBER WHIRLPOOL",
    "image_url": "http://omniacomponents.s3.eu-west-1.amazonaws.com/images/lambdaresized/500x500/loghi_marchio/Whirlpool/WHIRLPOOL.jpg"
  },
  {
    "code": "93X5373",
    "original_codes": [
      "93X5373"
    ],
    "description": "SHOCK ABSORBER - FAGOR 93X5373",
    "image_url": "http://omniacomponents.s3.eu-west-1.amazonaws.com/images/lambdaresized/500x500/loghi_marchio/Fagor/fagor.jpg"
  },
  {
    "code": "118869",
    "original_codes": [
      "00118869"
    ],
    "description": "SHOCK ABSORBER BOSCH",
    "image_url": "http://omniacomponents.s3.eu-west-1.amazonaws.com/images/lambdaresized/500x500/ORIGINALI/118869.jpg"
  },
  {
    "code": "383EER3001K",
    "original_codes": [
      "383EER3001G"
    ],
    "description": "SHOCK ABSORBER LG 383EER3001G",
    "image_url": "http://omniacomponents.s3.eu-west-1.amazonaws.com/images/lambdaresized/500x500/loghi_marchio/Lg/LG.jpg"
  },
  {
    "code": "SAR000BO",
    "original_codes": [
      "188222",
      "433761",
      "448032"
    ],
    "description": "SHOCK ABSORBER 90N - BOSCH 448032Holes Ø9-13mm, length: min 180mm, max 245mm,  90N.",
    "image_url": "http://omniacomponents.s3.eu-west-1.amazonaws.com/images/lambdaresized/500x500/LAVAGGIO/31_Ammortizzatori-balestre/SAR000BO.jpg"
  },
  {
    "code": "C00197934",
    "original_codes": [
      "197934"
    ],
    "description": "WASHING MACHINE SHOCK ABSORBER KIT - INDESIT - ORIGINAL 197934",
    "image_url": "http://omniacomponents.s3.eu-west-1.amazonaws.com/images/lambdaresized/500x500/LAVAGGIO/31_Ammortizzatori-balestre/C00197934.jpg"
  },
  {
    "code": "93700490",
    "original_codes": null,
    "description": "AMMORTIZZATORE LB CANDY - 93700490",
    "image_url": "http://omniacomponents.s3.eu-west-1.amazonaws.com/images/lambdaresized/500x500/loghi_marchio/Candy/Candy_logo.jpg"
  },
  {
    "code": "SAR000AR",
    "original_codes": [
      "086515",
      "141042"
    ],
    "description": "SHOCK ABSORBER KIT 2pcs 100N - ARISTON 086515-141042Kit 2pcs. 100N. Holes: Ø13+Ø7mm. Length: min.  183mm, max. 320mm.",
    "image_url": "http://omniacomponents.s3.eu-west-1.amazonaws.com/images/lambdaresized/500x500/LAVAGGIO/31_Ammortizzatori-balestre/SAR000AR.jpg"
  },
  {
    "code": "SAR000FA",
    "original_codes": [
      "LC4A009A5",
      "LC4C002A2"
    ],
    "description": "SHOCK ABSORBER 80N - FAGOR LC4A009A5Hole Ø8mm - Ø10mm, length: min 187mm, max 273mm.  With bracket. 80N.",
    "image_url": "http://omniacomponents.s3.eu-west-1.amazonaws.com/images/lambdaresized/500x500/loghi_marchio/Fagor/fagor.jpg"
  },
  {
    "code": "SAR001FA",
    "original_codes": [
      "481952918125",
      "AS0010676",
      "LC4D000A1"
    ],
    "description": "SHOCK ABSORBER 120N - FAGOR LC4C002A2-LC4A009A5Hole Ø7mm - Ø11mm, length: min 170mm, max 262mm.  With bracket. 120N.",
    "image_url": "http://omniacomponents.s3.eu-west-1.amazonaws.com/images/lambdaresized/500x500/LAVAGGIO/31_Ammortizzatori-balestre/SAR001FA.jpg"
  },
  {
    "code": "SAR002UN",
    "original_codes": null,
    "description": "SHOCK ABSORBER 120N - SUSPA120N. Length: max. 298mm, min.  183mm.",
    "image_url": ""
  },
  {
    "code": "SAR005GO",
    "original_codes": [
      "391857",
      "634801"
    ],
    "description": "GO TO SAR000GO80-120N. Length: 370mm.",
    "image_url": "http://omniacomponents.s3.eu-west-1.amazonaws.com/images/lambdaresized/500x500/LAVAGGIO/31_Ammortizzatori-balestre/SAR005GO.jpg"
  },
  {
    "code": "SAR005WH",
    "original_codes": [
      "481246648095"
    ],
    "description": "SHOCK ABSORBER 60N - WHIRLPOOL 48124664809560N. Holes: Ø10+10mm. Length: min. 163mm, max. 270 mm.",
    "image_url": "http://omniacomponents.s3.eu-west-1.amazonaws.com/images/lambdaresized/500x500/LAVAGGIO/31_Ammortizzatori-balestre/SAR005WH.jpg"
  },
  {
    "code": "SAR006GO",
    "original_codes": [
      "634802"
    ],
    "description": "GO TO SAR002GO65-85N. Length: max. 370mm.",
    "image_url": "http://omniacomponents.s3.eu-west-1.amazonaws.com/images/lambdaresized/500x500/LAVAGGIO/31_Ammortizzatori-balestre/SAR006GO.jpg"
  },
  {
    "code": "SAR007GO",
    "original_codes": [
      "559954"
    ],
    "description": "GO TO SAR008GO120N. Length: max. 287mm, min. 185mm. Holes: Ø12+8 mm.",
    "image_url": "http://omniacomponents.s3.eu-west-1.amazonaws.com/images/lambdaresized/500x500/LAVAGGIO/31_Ammortizzatori-balestre/SAR007GO.jpg"
  },
  {
    "code": "SAR020ZN",
    "original_codes": [
      "132255320",
      "132255333"
    ],
    "description": "SHOCK ABSORBER 80N SHORT - ZANUSSI 13225532080N, short. Fixing holes: max 223mm, min 150mm.   Holes: Ø11+11mm.",
    "image_url": "http://omniacomponents.s3.eu-west-1.amazonaws.com/images/lambdaresized/500x500/LAVAGGIO/31_Ammortizzatori-balestre/SAR020ZN.jpg"
  },
  {
    "code": "WTG209600",
    "original_codes": [
      "55X2928",
      "WTG209600"
    ],
    "description": "SHOCK ABSORBER FAGOR EX.55X2928",
    "image_url": "http://omniacomponents.s3.eu-west-1.amazonaws.com/images/lambdaresized/500x500/loghi_marchio/Fagor/fagor.jpg"
  },
  {
    "code": "7042790",
    "original_codes": [
      "7042790"
    ],
    "description": "SHOCK ABSORBER LIEBHERR",
    "image_url": "http://omniacomponents.s3.eu-west-1.amazonaws.com/images/lambdaresized/500x500/loghi_marchio/Liebherr/liebherr.png"
  },
  {
    "code": "677963",
    "original_codes": null,
    "description": "SHOCK ABSORBER BOSCH 677963",
    "image_url": ""
  },
  {
    "code": "45003399",
    "original_codes": [
      "45003399"
    ],
    "description": "SHOCK ABSORBER VESTEL",
    "image_url": "http://omniacomponents.s3.eu-west-1.amazonaws.com/images/lambdaresized/500x500/loghi_marchio/Vestel/VESTEL.jpg"
  },
  {
    "code": "2810430500",
    "original_codes": [
      "2810430500"
    ],
    "description": "WASHING MACHINE SHOCK ABSORBER BEKO 2810430500",
    "image_url": "http://omniacomponents.s3.eu-west-1.amazonaws.com/images/lambdaresized/500x500/loghi_marchio/Arcelik/arcelik-beko.jpg"
  },
  {
    "code": "2808210100",
    "original_codes": [
      "2808210100"
    ],
    "description": "SHOCK ABSORBER - BEKO 2808210100 - ORIGINAL",
    "image_url": "http://omniacomponents.s3.eu-west-1.amazonaws.com/images/lambdaresized/500x500/loghi_marchio/Arcelik/arcelik-beko.jpg"
  },
  {
    "code": "274404",
    "original_codes": [
      "274404"
    ],
    "description": "SHOCK ASSORBER GORENJE 274404",
    "image_url": "http://omniacomponents.s3.eu-west-1.amazonaws.com/images/lambdaresized/500x500/loghi_marchio/Gorenje/GORENJE.jpg"
  },
  {
    "code": "2001210200",
    "original_codes": null,
    "description": "SHOCK ABSORBER BOSCH",
    "image_url": "http://omniacomponents.s3.eu-west-1.amazonaws.com/images/lambdaresized/500x500/loghi_marchio/Arcelik/arcelik-beko.jpg"
  },
  {
    "code": "1322553510",
    "original_codes": null,
    "description": "SHOCK ABSORBER - ZANUSSI",
    "image_url": "http://omniacomponents.s3.eu-west-1.amazonaws.com/images/lambdaresized/500x500/loghi_marchio/Zanussi/ZANUSSI.jpg"
  },
  {
    "code": "1322553320",
    "original_codes": null,
    "description": "ZANUSSI SHOCK ASSORBER",
    "image_url": "http://omniacomponents.s3.eu-west-1.amazonaws.com/images/lambdaresized/500x500/loghi_marchio/Zanussi/ZANUSSI.jpg"
  },
  {
    "code": "SAR024ZN",
    "original_codes": [
      "1292348412"
    ],
    "description": "SHOCK ABSORBER 60N SHORT - ZANUSSI 129234841260N, short type. Holes: Ø10+10mm. Fixing holes:  max. 245mm, min. 163mm.",
    "image_url": "http://omniacomponents.s3.eu-west-1.amazonaws.com/images/lambdaresized/500x500/LAVAGGIO/31_Ammortizzatori-balestre/SAR024ZN.jpg"
  },
  {
    "code": "SAR008GO",
    "original_codes": [
      "559954"
    ],
    "description": "SHOCK ABSORBER 120N -  GORENJE 559954 - SUSPARD 18. 120N. Length: max. 287mm, min. 185mm.  Holes: Ø12+8mm.",
    "image_url": "http://omniacomponents.s3.eu-west-1.amazonaws.com/images/lambdaresized/500x500/loghi_marchio/Gorenje/GORENJE.jpg"
  },
  {
    "code": "SAR010MI",
    "original_codes": [
      "00118869",
      "04151285",
      "04500820",
      "04500823",
      "04500826",
      "06200778",
      "10095440",
      "118869",
      "4500826"
    ],
    "description": "SHOCK ABSORBER KIT 3pcs - MIELE 10095440+04151285 - SUSPAKit 3 pcs: 2 pcs of 10095440, 75N + 1 pcs of  04151285, 120N.",
    "image_url": "http://omniacomponents.s3.eu-west-1.amazonaws.com/images/lambdaresized/500x500/loghi_marchio/Miele/MIELE.jpg"
  }
]
