[{"name":"DISHWASHER DOOR LOCK - BEKO 1510600300","atet_code":"148AC09","omnia_code":"1510600300","sku":"2168433","price":"800","image_url":"https://atet-ricambi.it/en/images/148AC09?Size=400x200","description":""},{"name":"DOOR LOCK - SAMSUNG DC64-00653AType: KM-SA. 3 contacts. 16(6)A, 250V closing. 1A,  250V opening.","atet_code":"148SU01","omnia_code":"INT006SA","sku":"2123420","price":"660","image_url":"http://omniacomponents.s3.eu-west-1.amazonaws.com/images/lambdaresized/500x500/LAVAGGIO/12_Elettroserrature-Bloccoporta/INT006SA.jpg","description":""},{"name":"DOOR LOCK - LG 6601EN1003D EX.6601ER1005AType: KM-LL. 3 contacts. 16(6)A, 250V closing. 1A,  250V opening.","atet_code":"148EG00","omnia_code":"INT006LG","sku":"2123230","price":"750","image_url":"https://atet-ricambi.it/en/images/148EG00?Size=400x200","description":""},{"name":"DOOR LOCK - SAMSUNG DC64-01538AType: KM-SM. 3 contacts. 16(6)A, 250V closing. 1A,  250V opening.","atet_code":"148SU03","omnia_code":"INT007SA","sku":"2165444","price":"850","image_url":"http://omniacomponents.s3.eu-west-1.amazonaws.com/images/lambdaresized/500x500/LAVAGGIO/12_Elettroserrature-Bloccoporta/INT007SA.jpg","description":""},{"name":"DOOR LOCK - ATLANT 908092001900Tipo: KM-AT. T85. 16(6)A, 250V closing, 1A, 250V  opening. 3 contacts.","atet_code":"","omnia_code":"INT000AT","sku":"2168434","price":"580","image_url":"http://omniacomponents.s3.eu-west-1.amazonaws.com/images/lambdaresized/500x500/LAVAGGIO/12_Elettroserrature-Bloccoporta/INT000AT.jpg","description":""},{"name":"DOOR LOCK - HAIER0020400505BType: KM. 3 contacts. 16(6)A, 250V closing. 1A,  250V opening.","atet_code":"148HA04","omnia_code":"INT002HA","sku":"2168435","price":"590","image_url":"https://atet-ricambi.it/en/images/148HA04?Size=400x200","description":""},{"name":"DOOR LOCK - ARDO 651016770-481228058043Type: DL-LC. 16(6)/250 closing, 1(2)/250  opening.T85, 3 contacts.","atet_code":"148AK15","omnia_code":"INT014AD","sku":"2121235","price":"750","image_url":"https://atet-ricambi.it/en/images/148AK15?Size=400x200","description":""},{"name":"DOOR LOCK - IT WASH 39501003900 - ROLD DA062047Series: DA. T85, 4-5: 16(6)A 250V closing.1(2)A  250V opening. 3 contacts.","atet_code":"148IW00","omnia_code":"INT000IW","sku":"2168436","price":"730","image_url":"http://omniacomponents.s3.eu-west-1.amazonaws.com/images/lambdaresized/500x500/LAVAGGIO/12_Elettroserrature-Bloccoporta/INT000IW.jpg","description":""},{"name":"DOOR LOCK - HAIER Type: KM-1. 3 contacts. 250V, 16(6)A closing.  0(0)A opening.","atet_code":"","omnia_code":"INT003HA","sku":"2168437","price":"670","image_url":"http://omniacomponents.s3.eu-west-1.amazonaws.com/images/lambdaresized/500x500/LAVAGGIO/12_Elettroserrature-Bloccoporta/INT003HA.jpg","description":""},{"name":"DOOR LOCK - GORENJE 170966 - ORIGINALSeries DA. 16(6)A, 250V closing, 1(2)A, 250V opening. T85, 3 contacts.","atet_code":"148GR06","omnia_code":"INT006GO","sku":"2163739","price":"480","image_url":"https://atet-ricambi.it/en/images/148GR06?Size=400x200","description":""},{"name":"DOOR LOCK - ROLD DA005006Series: DA. 250V, 16(6)A closing, 1(2)A opening, 3  contacts.","atet_code":"148HA00","omnia_code":"INT001HA","sku":"2168438","price":"730","image_url":"https://atet-ricambi.it/en/images/148HA00?Size=400x200","description":""},{"name":"DOOR LOCK - GORENJE 170966 - ROLD DA077050Series DA. 16(6)A, 250V closing, 1(2)A, 250V  opening.  3 contacts.","atet_code":"148GR06","omnia_code":"INT004GO","sku":"2168509","price":"830","image_url":"https://atet-ricambi.it/en/images/148GR06?Size=400x200","description":""},{"name":"DOOR LOCK - ZANUSSI 808679501DL-LC2.  250V.","atet_code":"148ZN31","omnia_code":"INT036ZN","sku":"2168440","price":"990","image_url":"https://atet-ricambi.it/en/images/148ZN31?Size=400x200","description":""},{"name":"DOOR LOCK - ZANUSSI - ROLD DA058028-8010649Series: DA.  16(6)A 250V closing, 1(2)A 250V  opening. 3 contacts.","atet_code":"148ZN24","omnia_code":"INT002ZN","sku":"2168441","price":"730","image_url":"https://atet-ricambi.it/en/images/148ZN24?Size=400x200","description":""},{"name":"DOOR LOCK - SANGIORGIO 30191001701 - DA000038Series: DA. 3-2 16(6)A 250V closing. 1(2)A  250Vopening. T85, 3 contacts","atet_code":"148FA06","omnia_code":"INT004SG","sku":"2168442","price":"660","image_url":"https://atet-ricambi.it/en/images/148FA06?Size=400x200","description":""},{"name":"DOOR LOCK - BEKO 2805311600 - ORIGINAL","atet_code":"148AC08","omnia_code":"INT007AC 2805311600","sku":"2126168","price":"650","image_url":"https://atet-ricambi.it/en/images/148AC08?Size=400x200","description":""},{"name":"DOOR LOCK - ZANUSSI 3792030342Type: DL-LC. 16(6)/250V closing, 1(2)/250V  opening. 3 contacts.","atet_code":"148ZN13","omnia_code":"INT023ZN","sku":"2168443","price":"690","image_url":"https://atet-ricambi.it/en/images/148ZN13?Size=400x200","description":""},{"name":"DOOR LOCK - SANGIORGIO 55X7562 - DA00000816(6)A, 250V closing, 1(2)A, 250V opening. 3  contacts.","atet_code":"148FA06","omnia_code":"INT002SG = INT004SG","sku":"NE","price":"660","image_url":"https://atet-ricambi.it/en/images/148FA06?Size=400x200","description":""},{"name":"DOOR LOCK - FAGOR 55X7562 ZV446-M1Series: ZV-446. 250V 16(6)A closing, 1(1)Aopening.  T85, 3 contacts.","atet_code":"148FA06","omnia_code":"INT005FA","sku":"2168510","price":"660","image_url":"https://atet-ricambi.it/en/images/148FA06?Size=400x200","description":""},{"name":"DOOR LOCK - HAIER 00216001005900Type: KM-MD. 3 contacts. 16(6)A, 250V closing. 1A,  250V opening.","atet_code":"148HA05","omnia_code":"INT005HA","sku":"2168444","price":"800","image_url":"http://omniacomponents.s3.eu-west-1.amazonaws.com/images/lambdaresized/500x500/LAVAGGIO/12_Elettroserrature-Bloccoporta/INT005HA.jpg","description":""},{"name":"DOOR LOCK - ZANUSSI 50680374001250V, 16(4)A closing 0(0)A opening.  3  contacts.","atet_code":"","omnia_code":"INT017ZN","sku":"2168445","price":"780","image_url":"http://omniacomponents.s3.eu-west-1.amazonaws.com/images/lambdaresized/500x500/LAVAGGIO/12_Elettroserrature-Bloccoporta/INT017ZN.jpg","description":""},{"name":"DOOR LOCK - ZANUSSI 1084765013Type: DL-LC. 16(6)250V closing. 1(2)250V  opening.T85, 3 contacts.","atet_code":"148ZN34","omnia_code":"INT016ZN","sku":"2168226","price":"780","image_url":"https://atet-ricambi.it/en/images/148ZN34?Size=400x200","description":""},{"name":"DOOR LOCK BEKO METALFLEX ZV446T1","atet_code":"148AC05","omnia_code":"INT001AC 2805311400","sku":"2123712","price":"650","image_url":"","description":""},{"name":"DOOR LOCK - ARISTON - ROLD DA003041Series DA, 250V. 3  contacts.","atet_code":"148AR05","omnia_code":"INT009AR","sku":"2121242","price":"830","image_url":"http://omniacomponents.s3.eu-west-1.amazonaws.com/images/lambdaresized/500x500/LAVAGGIO/12_Elettroserrature-Bloccoporta/INT009AR.jpg","description":""},{"name":"DOOR LOCK - ATLANT 908092001902 - ZV449T2250V, 6(4)A closing, 1(1)A opening. 3  contacts.","atet_code":"","omnia_code":"INT002AT","sku":"2168450","price":"840","image_url":"http://omniacomponents.s3.eu-west-1.amazonaws.com/images/lambdaresized/500x500/LAVAGGIO/12_Elettroserrature-Bloccoporta/INT002AT.jpg","description":""},{"name":"DOOR LOCK - ZANUSSI 1326208012Series: DA. 4-5 16(6)A, 250V closed, 1(2) 250V  opening. 3 contacts.","atet_code":"148ZN35","omnia_code":"INT033ZN","sku":"2168451","price":"1040","image_url":"https://atet-ricambi.it/en/images/148ZN35?Size=400x200","description":""},{"name":"DOOR LOCK - INDESIT C00306612250V 16(6)A closing 1(1)A opening T85. 3 contacts.","atet_code":"148ID22","omnia_code":"INT019ID","sku":"2168452","price":"830","image_url":"https://atet-ricambi.it/en/images/148ID22?Size=400x200","description":""},{"name":"DOOR LOCK - SANGIORGIO 3019100400RType: 626. 250V, 16(4)A closing, 0(0)A opening.  T85, 3 contacts.","atet_code":"","omnia_code":"INT005SG","sku":"2125245","price":"910","image_url":"http://omniacomponents.s3.eu-west-1.amazonaws.com/images/lambdaresized/500x500/LAVAGGIO/12_Elettroserrature-Bloccoporta/INT005SG.jpg","description":""},{"name":"DOOR LOCK - HOTPOINT 1604781Series: ZV-446. 250V 16(6)A closing, 1(1)Aopening.  T85, 3 contacts.","atet_code":"148HP01","omnia_code":"INT001HP","sku":"2168453","price":"800","image_url":"https://atet-ricambi.it/en/images/148HP01?Size=400x200","description":""},{"name":"DOOR LOCK - SAMSUNG DC64-01538A - BITRON","atet_code":"","omnia_code":"INT010SA","sku":"","price":"","image_url":"http://omniacomponents.s3.eu-west-1.amazonaws.com/images/lambdaresized/500x500/loghi_marchio/Samsung/SAMSUNG.jpg","description":""},{"name":"DOOR LOCK - INDESIT 294848Type: DL-S2. 250V, 4-5 16(6)  closing/opening.","atet_code":"148ID25","omnia_code":"INT018ID","sku":"2168454","price":"1100","image_url":"https://atet-ricambi.it/en/images/148ID25?Size=400x200","description":""},{"name":"DOOR LOCK - ZANUSSI 8070202018Type: DL-LC. 16(6) 250V closed, 1(2) 250V opening.  3 contacts.","atet_code":"148ZN29","omnia_code":"INT022ZN","sku":"2166507","price":"990","image_url":"https://atet-ricambi.it/en/images/148ZN29?Size=400x200","description":""},{"name":"DOOR LOCK - ARDO 651016775","atet_code":"148AC04","omnia_code":"INT008AC","sku":"2125518","price":"1910","image_url":"https://atet-ricambi.it/en/images/148AC04?Size=400x200","description":""},{"name":"DOOR LOCK - INDESIT 095979Series: DA. 3-2 16(6)A 250V closing. 1A  250Vopening. T85, 2 contacts.","atet_code":"","omnia_code":"INT006ID","sku":"2168455","price":"950","image_url":"http://omniacomponents.s3.eu-west-1.amazonaws.com/images/lambdaresized/500x500/LAVAGGIO/12_Elettroserrature-Bloccoporta/INT006ID.jpg","description":""},{"name":"DOOR LOCK - LG EBF49827801/02Type: DM-01/02. 4 contacts. 16(6)A, 250V  closing.","atet_code":"148EG05","omnia_code":"INT007LG","sku":"2168507","price":"965","image_url":"http://omniacomponents.s3.eu-west-1.amazonaws.com/images/lambdaresized/500x500/LAVAGGIO/12_Elettroserrature-Bloccoporta/INT007LG.jpg","description":""},{"name":"DOOR LOCK - ZANUSSI 132693902535Type: DL-LC. 16(6) 250V closed, 1(2) 250V opening.  3 contacts.","atet_code":"","omnia_code":"INT035ZN","sku":"2168511","price":"980","image_url":"http://omniacomponents.s3.eu-west-1.amazonaws.com/images/lambdaresized/500x500/LAVAGGIO/12_Elettroserrature-Bloccoporta/INT035ZN.jpg","description":""},{"name":"DOOR LOCK - ZANUSSI 50680372005250V, 16(4)A closing, 0(0)A  opening.","atet_code":"","omnia_code":"INT003ZN","sku":"2168512","price":"980","image_url":"http://omniacomponents.s3.eu-west-1.amazonaws.com/images/lambdaresized/500x500/LAVAGGIO/12_Elettroserrature-Bloccoporta/INT003ZN.jpg","description":""},{"name":"DOOR LOCK - VESTEL 32024465 - ZV446M8250V 16(6)A closing, 1(1)A opening. T85, 3 contact s.","atet_code":"148VE04","omnia_code":"INT003VE","sku":"2168513","price":"800","image_url":"https://atet-ricambi.it/en/images/148VE04?Size=400x200","description":""},{"name":"DOOR LOCK - INDESIT C00309745 - METALFLEX ZV449E2","atet_code":"148ID26","omnia_code":"INT020ID","sku":"2168514","price":"755","image_url":"https://atet-ricambi.it/en/images/148ID26?Size=400x200","description":""},{"name":"DOOR LOCK - ZANUSSI 1552374017Type: ZV-446. 250V, 16(6)A closed, 1(1)A opening.  3 contacts.","atet_code":"ZAN000001552374017","omnia_code":"INT028ZN","sku":"2168516","price":"2220","image_url":"http://omniacomponents.s3.eu-west-1.amazonaws.com/images/lambdaresized/500x500/LAVAGGIO/12_Elettroserrature-Bloccoporta/INT028ZN.jpg","description":""},{"name":"DOOR LOCK - INDESIT 141683Type: DDL-SR. 4-5 16(6) 250V closing, opening.T85,  3 contatti.","atet_code":"148HP04","omnia_code":"INT002ID","sku":"2168517","price":"1205","image_url":"http://omniacomponents.s3.eu-west-1.amazonaws.com/images/lambdaresized/500x500/LAVAGGIO/12_Elettroserrature-Bloccoporta/INT002ID.jpg","description":""},{"name":"DOOR LOCK - ZANUSSI   50232811005","atet_code":" ZAN50232811005","omnia_code":"INT018ZN","sku":"2168518","price":"3410","image_url":"http://omniacomponents.s3.eu-west-1.amazonaws.com/images/lambdaresized/500x500/LAVAGGIO/12_Elettroserrature-Bloccoporta/INT018ZN.jpg","description":""},{"name":"DOOR LOCK - ZANUSSISeries: DK. 4-5 16(6)A, 250V. 3  contacts.","atet_code":"","omnia_code":"INT032ZN","sku":"","price":"","image_url":"http://omniacomponents.s3.eu-west-1.amazonaws.com/images/lambdaresized/500x500/LAVAGGIO/12_Elettroserrature-Bloccoporta/INT032ZN.jpg","description":""},{"name":"DOOR LOCK - SANGIORGIO 30191001801 - DA000738Series: DA. 3-2 16(6)A 250V closing. 1A  250Vopening. T85, 3 contacts.","atet_code":"148SG09","omnia_code":"INT003SG","sku":"2168519","price":"1205","image_url":"http://omniacomponents.s3.eu-west-1.amazonaws.com/images/lambdaresized/500x500/LAVAGGIO/12_Elettroserrature-Bloccoporta/INT003SG.jpg","description":""},{"name":"DISHWASHER DOOR LOCK - INDESIT 274116With  connector.","atet_code":"148ID16","omnia_code":"INT503ID","sku":"2168520","price":"1300","image_url":"https://atet-ricambi.it/en/images/148ID16?Size=400x200","description":""},{"name":"DOOR LOCK - PHILCO-SAMSUNG 116102260-DC61-20205B","atet_code":"","omnia_code":"INT003PH","sku":"NE","price":"","image_url":"http://omniacomponents.s3.eu-west-1.amazonaws.com/images/lambdaresized/500x500/LAVAGGIO/12_Elettroserrature-Bloccoporta/INT003PH.jpg","description":""},{"name":"DOOR LOCK - VESTEL 32018336Type: DL-S2. 10(6) 250V  closing/opening.","atet_code":"148VE02","omnia_code":"INT002VE","sku":"2166964","price":"1130","image_url":"https://atet-ricambi.it/en/images/148VE02?Size=400x200","description":""},{"name":"DOOR LOCK - ZANUSSI 1462229202 - ROLD DA045668Series: Top. 16(6)A, 250V closing, 1(2)A, 250V  opening. 3 contacts.","atet_code":"148ZN32","omnia_code":"INT020ZN","sku":"2168521","price":"1180","image_url":"http://omniacomponents.s3.eu-west-1.amazonaws.com/images/lambdaresized/500x500/LAVAGGIO/12_Elettroserrature-Bloccoporta/INT020ZN.jpg","description":""},{"name":"DOOR LOCK - ZANUSSISeries: DM. 250V, 16(6)A closed, 1A opening. 3  contacts.","atet_code":"148ZN28","omnia_code":"INT034ZN","sku":"NE","price":"","image_url":"http://omniacomponents.s3.eu-west-1.amazonaws.com/images/lambdaresized/500x500/LAVAGGIO/12_Elettroserrature-Bloccoporta/INT034ZN.jpg","description":""},{"name":"DOOR LOCK - AEG-SMEG 018535 - ROLD 57013Series: DS88. 250V, 2C-3L, 16(4)A closing, 0(0)A o pening. 3 contacts.","atet_code":"GIA49018535","omnia_code":"INT000SM","sku":"2168523","price":"1100","image_url":"http://omniacomponents.s3.eu-west-1.amazonaws.com/images/lambdaresized/500x500/LAVAGGIO/12_Elettroserrature-Bloccoporta/INT000SM.jpg","description":""},{"name":"DOOR LOCK - ARISTON ZV445P5Model: P5. 250V, 16(4)A closing, 0(0)A  opening.T85, 3 contacts.","atet_code":"148AR03","omnia_code":"INT000AR","sku":"2121253","price":"590","image_url":"http://omniacomponents.s3.eu-west-1.amazonaws.com/images/lambdaresized/500x500/LAVAGGIO/12_Elettroserrature-Bloccoporta/INT000AR.jpg","description":""},{"name":"DOOR LOCK - ZANUSSI 132693800Series: DF. 4-5 16(6)A, 250V. 4  contacts.","atet_code":"","omnia_code":"INT030ZN","sku":"NE","price":"","image_url":"http://omniacomponents.s3.eu-west-1.amazonaws.com/images/lambdaresized/500x500/LAVAGGIO/12_Elettroserrature-Bloccoporta/INT030ZN.jpg","description":""},{"name":"DOOR LOCK - ZANUSSI ZV445B1","atet_code":"","omnia_code":"INT000ZN","sku":"2168524","price":"1130","image_url":"http://omniacomponents.s3.eu-west-1.amazonaws.com/images/lambdaresized/500x500/LAVAGGIO/12_Elettroserrature-Bloccoporta/INT000ZN.jpg","description":""},{"name":"DOOR LOCK ZANUSSI 1328469000-ROLD DKS02511Series: DK. 3 contacts. 4-5 16(6)A,  250V.","atet_code":"148ZN28","omnia_code":"INT025ZN","sku":"2168522","price":"1460","image_url":"https://atet-ricambi.it/en/images/148ZN28?Size=400x200","description":""},{"name":"DOOR LOCK - ZANUSSI 108476514545Type: DL-LC. 16(6) 250V closed, 1(2) 250V opening.  3 contacts.","atet_code":"","omnia_code":"INT031ZN","sku":"2168528","price":"1130","image_url":"http://omniacomponents.s3.eu-west-1.amazonaws.com/images/lambdaresized/500x500/LAVAGGIO/12_Elettroserrature-Bloccoporta/INT031ZN.jpg","description":""},{"name":"DOOR LOCK - POLAR 2805310100 - ZV445C1","atet_code":"148PL00","omnia_code":"INT000PO","sku":"2168531","price":"770","image_url":"https://atet-ricambi.it/en/images/148PL00?Size=400x200","description":""},{"name":"DOOR LOCK ARDO","atet_code":"","omnia_code":"651016758","sku":"NE","price":"","image_url":"http://omniacomponents.s3.eu-west-1.amazonaws.com/images/lambdaresized/500x500/loghi_marchio/Ardo/Ardo.png","description":""},{"name":"DOOR LOCK - IGNIS 481969018108 - ZV445T4","atet_code":"148IG08","omnia_code":"INT000WH","sku":"2121804","price":"780","image_url":"https://atet-ricambi.it/en/images/148IG08?Size=400x200","description":""},{"name":"DOOR LOCK - DAEWOO 3619047250Type: DL-S2. 4-5 16(6)/250V closing-opening. 4  contacts.","atet_code":"148DA02","omnia_code":"INT001DW","sku":"2168535","price":"1200","image_url":"https://atet-ricambi.it/en/images/148DA02?Size=400x200","description":""},{"name":"DOOR LOCK - FAGOR L39A000I6 - ZV445M2","atet_code":"148FA02","omnia_code":"INT000FA","sku":"2168536","price":"620","image_url":"https://atet-ricambi.it/en/images/148FA02?Size=400x200","description":""},{"name":"DOOR LOCK WHIRLPOOL","atet_code":"","omnia_code":"481071423921","sku":"NE","price":"","image_url":"http://omniacomponents.s3.eu-west-1.amazonaws.com/images/lambdaresized/500x500/loghi_marchio/Whirlpool/WHIRLPOOL.jpg","description":""},{"name":"DOOR LOCK - BOSCH 610147 - SKLDM series, 3 contacts. 16(6)A 250V~ closing, 1(2)A  250V~ opening.","atet_code":"148BH06","omnia_code":"INT016BO","sku":"2165453","price":"1300","image_url":"http://omniacomponents.s3.eu-west-1.amazonaws.com/images/lambdaresized/500x500/LAVAGGIO/12_Elettroserrature-Bloccoporta/INT016BO.jpg","description":""},{"name":"DOOR LOCK - WHIRLPOOL 480111101392Type: DL-LC. 10(6) 250V closing. 1(2) 250Vopening.  T85, 3 contacts.","atet_code":"148IG25","omnia_code":"INT017WH","sku":"2167256","price":"1490","image_url":"https://atet-ricambi.it/en/images/148IG25?Size=400x200","description":""},{"name":"DOOR LOCK - ATLANTTipo: DM-A. T85. 16(6)A, 250V closing/ opening. 3  contacts.","atet_code":"","omnia_code":"INT001AT","sku":"2168537","price":"1300","image_url":"http://omniacomponents.s3.eu-west-1.amazonaws.com/images/lambdaresized/500x500/LAVAGGIO/12_Elettroserrature-Bloccoporta/INT001AT.jpg","description":""},{"name":"DOOR LOCK - HOTPOINT 1602390 - ZV445M4","atet_code":"148HP01","omnia_code":"INT000HP","sku":"2168453","price":"1160","image_url":"https://atet-ricambi.it/en/images/148HP01?Size=400x200","description":""},{"name":"DOOR LOCK - BOSCH 182154 - SKLSeries: DA.  250V, 16(6)A closing, 1(1)A  opening.","atet_code":"148BY09","omnia_code":"INT006BO","sku":"2122054","price":"1730","image_url":"http://omniacomponents.s3.eu-west-1.amazonaws.com/images/lambdaresized/500x500/LAVAGGIO/12_Elettroserrature-Bloccoporta/INT017BO.jpg","description":""},{"name":"GRUPPO SERRATURA ORIGINALE SMEG 697690201","atet_code":"SME697690201","omnia_code":"697690201","sku":"","price":"0","image_url":"http://omniacomponents.s3.eu-west-1.amazonaws.com/images/lambdaresized/500x500/loghi_marchio/Smeg/SMEG.jpg","description":""},{"name":"DOOR LOCK - INDESIT 299278-264161 - ROLD DKS01872Series DK. 16(6)A,  250V.","atet_code":"148ID14","omnia_code":"INT012ID","sku":"2164866","price":"1440","image_url":"http://omniacomponents.s3.eu-west-1.amazonaws.com/images/lambdaresized/500x500/LAVAGGIO/12_Elettroserrature-Bloccoporta/INT012ID.jpg","description":""},{"name":"DOOR LOCK - LG EBF61315801 - BITRONType: DM-A-01. 4 contacts. 16(6)A, 250V  closing/opening.","atet_code":"148EG06","omnia_code":"INT010LG","sku":"2168538","price":"1270","image_url":"https://atet-ricambi.it/en/images/148EG06?Size=400x200","description":""},{"name":"DOOR LOCK - ZANUSSI 8084553018 - DKS10619Series: DK. 16(6)A,  250V.","atet_code":"148ZN30","omnia_code":"INT024ZN","sku":"2168061","price":"1800","image_url":"https://atet-ricambi.it/en/images/148ZN30?Size=400x200","description":""},{"name":"DOOR LOCK - WHIRLPOOL 481927138179Series DS 88/T3. 250V 16(4)A closing,  0(0)Aopening. 3 contacts.","atet_code":"148IG13","omnia_code":"INT007WH","sku":"2168539","price":"1180","image_url":"https://atet-ricambi.it/en/images/148IG13?Size=400x200","description":""},{"name":"DOOR LOCK - PHILCO 052797 - ROLD 57701Series:  DS88.","atet_code":"","omnia_code":"INT002PH","sku":"2168540","price":"1520","image_url":"http://omniacomponents.s3.eu-west-1.amazonaws.com/images/lambdaresized/500x500/LAVAGGIO/12_Elettroserrature-Bloccoporta/INT002PH.jpg","description":""},{"name":"DOOR LOCK - BOSCH 638259 - ORIGINALT85, 16(6)A, 250V. 3 contacts.","atet_code":"148BH09","omnia_code":"INT015BO","sku":"2167884","price":"2270","image_url":"http://omniacomponents.s3.eu-west-1.amazonaws.com/images/lambdaresized/500x500/LAVAGGIO/12_Elettroserrature-Bloccoporta/INT015BO.jpg","description":""},{"name":"DOOR LOCK - WHIRLPOOL 481010609474Type: DL-L02. 10(6) 250V closed, 1(2) 250V  opening.","atet_code":"148IG30","omnia_code":"INT021WH","sku":"2168542","price":"1000","image_url":"http://omniacomponents.s3.eu-west-1.amazonaws.com/images/lambdaresized/500x500/LAVAGGIO/12_Elettroserrature-Bloccoporta/INT021WH.jpg","description":""},{"name":"DOOR LOCK - INDESIT 254755 - ROLD DKS01570Series DK. 4-5 16(6)A 250V. T85, 1E4. 3  contacts.","atet_code":"148ID13","omnia_code":"INT016ID","sku":"2124687","price":"1300","image_url":"http://omniacomponents.s3.eu-west-1.amazonaws.com/images/lambdaresized/500x500/LAVAGGIO/12_Elettroserrature-Bloccoporta/INT016ID.jpg","description":""},{"name":"DOOR LOCK - PHILCO 57001 - ROLD 57001250V, 2C-3L: 16(4)A closing, 0(0)A opening, 3  contacts.","atet_code":"","omnia_code":"INT000PH","sku":"NE","price":"","image_url":"http://omniacomponents.s3.eu-west-1.amazonaws.com/images/lambdaresized/500x500/LAVAGGIO/12_Elettroserrature-Bloccoporta/INT000PH.jpg","description":""},{"name":"DOOR LOCK - HAIER 0020400505D - ROLD DA252204Series DA, with Micro N/A. Closing: 16(6)A, 250V.  Opening: 1A, 250V. 5 contacts.","atet_code":"","omnia_code":"INT008HA","sku":"NE","price":"","image_url":"","description":""},{"name":"DOOR LOCK - HAIER 0024000128AType: DM-7. 3 contacts. 250V,  16(6)A.","atet_code":"148HA02","omnia_code":"INT004HA","sku":"2168543","price":"1110","image_url":"https://atet-ricambi.it/en/images/148HA02?Size=400x200","description":""},{"name":"DOOR LOCK - FAGOR THOMSON BRANDT 55X3548","atet_code":"148FA04","omnia_code":"INT004FA","sku":"2165063","price":"1600","image_url":"https://atet-ricambi.it/en/images/148FA04?Size=400x200","description":""},{"name":"DOOR LOCK - ZANUSSI 1246554008Type: BP P/5. 1-2 16(4)250V closing, opening.  4-516(4)250V closing, 0(0)250V opening.5-6  0,5(0,5)250V closing, opening. T85, 3  contacts","atet_code":"148ZN19 OK","omnia_code":"INT013ZN NE","sku":"2168544","price":"1800","image_url":"https://atet-ricambi.it/en/images/148ZN19?Size=400x200","description":""},{"name":"DOOR LOCK - BOSCH 633765-619468Type: 881. 250V, 50/60Hz, T85. 16(6)A closing  1(1)A opening. 3 contacts.","atet_code":"148BH08","omnia_code":"INT014BO","sku":"2165928","price":"1580","image_url":"http://omniacomponents.s3.eu-west-1.amazonaws.com/images/lambdaresized/500x500/LAVAGGIO/12_Elettroserrature-Bloccoporta/INT014BO.jpg","description":""},{"name":"DOOR LOCK - SMEG 814490983 - ROLD DFF51809Serie: DF. 3 contacts. 4-5 16(6)A,  250V.","atet_code":"148SM06","omnia_code":"INT002SM","sku":"2168545","price":"1600","image_url":"https://atet-ricambi.it/en/images/148SM06?Size=400x200","description":""},{"name":"DOOR LOCK - SAMSUNG DC64-00652DBlack. T85, 250V, 50/60Hz. 7 contacts.","atet_code":"148SU04","omnia_code":"INT009SA","sku":"2168546","price":"2200","image_url":"http://omniacomponents.s3.eu-west-1.amazonaws.com/images/lambdaresized/500x500/LAVAGGIO/12_Elettroserrature-Bloccoporta/INT009SA.jpg","description":""},{"name":"DOOR LOCK - DAEWOO - ROLD DFF11110DF series. 4-5 16(6)A 125V. 1E4. 4 contacts.","atet_code":"148DA01","omnia_code":"INT002DW","sku":"2168547","price":"1700","image_url":"http://omniacomponents.s3.eu-west-1.amazonaws.com/images/lambdaresized/500x500/LAVAGGIO/12_Elettroserrature-Bloccoporta/INT002DW.jpg","description":""},{"name":"DISHWASHER DOOR LOCK - SMEG 2200018014","atet_code":"","omnia_code":"INT501SM","sku":"NE","price":"","image_url":"http://omniacomponents.s3.eu-west-1.amazonaws.com/images/lambdaresized/500x500/LAVAGGIO/12_Elettroserrature-Bloccoporta/INT501SM.jpg","description":""},{"name":"DOOR LOCK - LG EBF49827801 - ROLD DFF80850UL version. DF series, 16A RES/6A make, 16A  REG/6Abreak. 4 contact.","atet_code":"148EG05","omnia_code":"INT009LG INT007LG OK","sku":"2168507","price":"970","image_url":"https://atet-ricambi.it/en/images/148EG05?Size=400x200","description":""},{"name":"DOOR LOCK - INDESIT","atet_code":"148ID22","omnia_code":"306612 INT019ID ","sku":"2168452","price":"830","image_url":"https://atet-ricambi.it/en/images/148ID22?Size=400x200","description":""},{"name":"DOOR LOCK - DAEWOO - ROLD DFF01007Series: DF. 4 contacts. 4-5 16(6)A,  250V.","atet_code":"148DA00","omnia_code":"INT000DW","sku":"2168548","price":"1700","image_url":"http://omniacomponents.s3.eu-west-1.amazonaws.com/images/lambdaresized/500x500/LAVAGGIO/12_Elettroserrature-Bloccoporta/INT000DW.jpg","description":""},{"name":"DOOR LOCK - INDESIT 051438 - ROLD 57711 - 051438Series: DS 88. 250V, 2C-3L, 16(4)A closing, 0(0)A  opening.","atet_code":"148AR07","omnia_code":"INT001ID","sku":"2168549","price":"1420","image_url":"https://atet-ricambi.it/en/images/148AR07?Size=400x200","description":""},{"name":"DISHWASHER DOOR LOCK KIT - ZANUSSI 4055260212 - ORIGINAL","atet_code":"ZAN000004055260212","omnia_code":"INT501ZN","sku":"NE","price":"","image_url":"http://omniacomponents.s3.eu-west-1.amazonaws.com/images/lambdaresized/500x500/LAVAGGIO/12_Elettroserrature-Bloccoporta/INT501ZN.jpg","description":""},{"name":"DOOR LOCK - LG EBF61315801Type: DM-A-01. 4 contacts. 16(6)A, 250V  closing/opening.","atet_code":"148EG06","omnia_code":"INT008LG","sku":"NE - POGLEDATI INT010LG","price":"","image_url":"https://atet-ricambi.it/en/images/148EG06?Size=400x200","description":""},{"name":"DOOR LOCK - ARCELIK - BEKO 2004030000Type: DL-LC. 16(6)/250V closing, 1(2)/250V  opening. 3 contacts.","atet_code":"148AC06","omnia_code":"INT009AC","sku":"2168550","price":"1650","image_url":"https://atet-ricambi.it/en/images/148AC06?Size=400x200","description":""},{"name":"DOOR LOCK - INDESIT 272452 - ROLD DFF31876DF series. 16(6)A, 250V. T85. 3  contacts.","atet_code":"148ID11","omnia_code":"INT014ID","sku":"2168551","price":"1840","image_url":"http://omniacomponents.s3.eu-west-1.amazonaws.com/images/lambdaresized/500x500/LAVAGGIO/12_Elettroserrature-Bloccoporta/INT014ID.jpg","description":""},{"name":"GRUPPO SERRATURA ORIGINALE SMEG 697690215","atet_code":"SME697690215","omnia_code":"697690215","sku":"NE","price":"","image_url":"http://omniacomponents.s3.eu-west-1.amazonaws.com/images/lambdaresized/500x500/loghi_marchio/Smeg/SMEG.jpg","description":""},{"name":"DOOR LOCK - BLOMBERG 57015Series: DS 88. T85. 250V 2C-3L 16(4)A  closing,0(0)A opening. 3L-4 0,50(0,5)A. 3  contacts.","atet_code":"","omnia_code":"INT000BL","sku":"2168552","price":"1840","image_url":"http://omniacomponents.s3.eu-west-1.amazonaws.com/images/lambdaresized/500x500/LAVAGGIO/12_Elettroserrature-Bloccoporta/INT000BL.jpg","description":""},{"name":"DISHWASHER DOOR LOCK - SMEG 697690208Dishwasher door lock for door with double  microswitch.","atet_code":"148SM08","omnia_code":"INT500SM ","sku":"2168553","price":"2120","image_url":"https://atet-ricambi.it/en/images/148SM08?Size=400x200","description":""},{"name":"DOOR LOCK - SAMSUNG DC34-00026AType: DM-7. 3 contacts. 16(6)A, 250V.","atet_code":"148SU08","omnia_code":"INT011SA INT008SA OK","sku":"2166592","price":"1100","image_url":"http://omniacomponents.s3.eu-west-1.amazonaws.com/images/lambdaresized/500x500/LAVAGGIO/12_Elettroserrature-Bloccoporta/INT011SA.jpg","description":""},{"name":"DOOR LOCK - MAYC-OSTEIN 57604Series DS 88/T3. 250V 16(4)A closing 0(0)A  opening3 contacts.","atet_code":"148ZW07","omnia_code":"INT000MO","sku":"2168554","price":"1890","image_url":"https://atet-ricambi.it/en/images/148ZW07?Size=400x200","description":""},{"name":"DOOR LOCK WHIRLPOOL","atet_code":"148IG27","omnia_code":"481075043881","sku":"2165921","price":"850","image_url":"http://omniacomponents.s3.eu-west-1.amazonaws.com/images/lambdaresized/500x500/ORIGINALI/481075043881.jpg","description":""},{"name":"DOOR LOCK - SAMSUNG DC34-00025B 12V.","atet_code":"","omnia_code":"INT012SA","sku":"NE","price":"","image_url":"http://omniacomponents.s3.eu-west-1.amazonaws.com/images/lambdaresized/500x500/loghi_marchio/Samsung/SAMSUNG.jpg","description":""},{"name":"DOOR LOCK - WHIRLPOOL 480111101392Type: DL-LC. 10(6)/250V closing, 1(2)/250V  opening.","atet_code":"148IG25","omnia_code":"480111101392","sku":"2167256","price":"1420","image_url":"https://atet-ricambi.it/en/images/148IG25?Size=400x200","description":""},{"name":"DOOR LOCK - PHILCO 036683 - ROLD 57201","atet_code":"WHIC00036683","omnia_code":"INT001PH","sku":"2168555","price":"1900","image_url":"http://omniacomponents.s3.eu-west-1.amazonaws.com/images/lambdaresized/500x500/LAVAGGIO/12_Elettroserrature-Bloccoporta/INT001PH.jpg","description":""},{"name":"DOOR LOCK INDESIT","atet_code":"","omnia_code":"142615","sku":"NE","price":"","image_url":"http://omniacomponents.s3.eu-west-1.amazonaws.com/images/lambdaresized/500x500/loghi_marchio/Whirlpool/WHIRLPOOL.jpg","description":""},{"name":"DOOR LOCK - CANDY","atet_code":"","omnia_code":"90489211","sku":"NE","price":"","image_url":"http://omniacomponents.s3.eu-west-1.amazonaws.com/images/lambdaresized/500x500/loghi_marchio/Candy/Candy_logo.jpg","description":""},{"name":"DISHWASHER DOOR LOCK - ZANUSSI 1113150609With holder. 2 contacts.","atet_code":"146ZN12","omnia_code":"1113150609","sku":"2164422","price":"2120","image_url":"http://omniacomponents.s3.eu-west-1.amazonaws.com/images/lambdaresized/500x500/LAVAGGIO/12_Elettroserrature-Bloccoporta/1113150609.jpg","description":""},{"name":"MERLONI DISHWASHER DOOR LOCK","atet_code":"148ID25","omnia_code":"294848 INT018ID","sku":"2168454","price":"1090","image_url":"https://atet-ricambi.it/en/images/148ID25?Size=400x200","description":""},{"name":"DOOR LOCK - ARDO 57204 - 813010004","atet_code":"148AK09","omnia_code":"INT006AD","sku":"2168556","price":"2170","image_url":"https://atet-ricambi.it/en/images/148AK09?Size=400x200","description":""},{"name":"DOOR LOCK - BOSCH 263334 - BITRONType: BP. 16(6)/250V closing, 1(2)/250V opening. 3  contacts.","atet_code":"","omnia_code":"INT012BO","sku":"2126090","price":"2240","image_url":"http://omniacomponents.s3.eu-west-1.amazonaws.com/images/lambdaresized/500x500/LAVAGGIO/12_Elettroserrature-Bloccoporta/INT012BO.jpg","description":""},{"name":"DOOR LOCK - BOSCH 178567 - BITRONType: BP. 16(6)/250V closing, 1(2)/250V opening. 3  contacts.","atet_code":"","omnia_code":"INT010BO","sku":"2168557","price":"2200","image_url":"http://omniacomponents.s3.eu-west-1.amazonaws.com/images/lambdaresized/500x500/LAVAGGIO/12_Elettroserrature-Bloccoporta/INT010BO.jpg","description":""},{"name":"DISHWASHER DOOR LOCK INDESIT","atet_code":"148AR11","omnia_code":"085357","sku":"2123645","price":"1650","image_url":"http://omniacomponents.s3.eu-west-1.amazonaws.com/images/lambdaresized/500x500/loghi_marchio/Whirlpool/WHIRLPOOL.jpg","description":""},{"name":"DOOR LOCK CANDY 49017982","atet_code":"GIA49017982","omnia_code":"49017982","sku":"2166090","price":"2360","image_url":"http://omniacomponents.s3.eu-west-1.amazonaws.com/images/lambdaresized/500x500/loghi_marchio/Candy/Candy_logo.jpg","description":""},{"name":"DOOR LOCK - WHIRLPOOL 481010602648 - ROLD DKS66603DK series. 1-2 16(6)A 250V. 3 contacts.","atet_code":"148ID21","omnia_code":"INT023WH","sku":"2168558","price":"1700","image_url":"https://atet-ricambi.it/en/images/148ID21?Size=400x200","description":""},{"name":"DOOR LOCK - CANDY ZEROWATT 57723 - 90483702","atet_code":"148ZW05","omnia_code":"INT001ZW","sku":"2168559","price":"1980","image_url":"https://atet-ricambi.it/en/images/148ZW05?Size=400x200","description":""},{"name":"DOOR LOCK - INDESIT 085610Type: BP P/5-R. M-C: 16 (4)A, 250V  closing/opening. 5-6: 16(4), 250V closing - 0,  250V opening. T85, 3 contacts.","atet_code":"","omnia_code":"INT017ID","sku":"2121234","price":"1890","image_url":"http://omniacomponents.s3.eu-west-1.amazonaws.com/images/lambdaresized/500x500/LAVAGGIO/12_Elettroserrature-Bloccoporta/INT017ID.jpg","description":""},{"name":"DOOR LOCK - BOSCH 613070250V, 50/60Hz, 3 contacts.","atet_code":"148BH05","omnia_code":"INT020BO","sku":"2168560","price":"1650","image_url":"https://atet-ricambi.it/en/images/148BH05?Size=400x200","description":""},{"name":"DOOR LOCK - WHIRLPOOL 481010474505Type: BP P/5. M-C 16(4)/250V closing opening.4-5  16(4)/250V closing, 0/250V opening. 3 contacts","atet_code":"148IG31","omnia_code":"INT022WH","sku":"2168561","price":"2430","image_url":"https://atet-ricambi.it/en/images/148IG31?Size=400x200","description":""},{"name":"DISHWASHER DOOR LOCK INDESIT C00285843","atet_code":"WHIC00285843","omnia_code":"C00285843","sku":"2168562","price":"3150","image_url":"http://omniacomponents.s3.eu-west-1.amazonaws.com/images/lambdaresized/500x500/LAVAGGIO/12_Elettroserrature-Bloccoporta/C00285843.jpg","description":""},{"name":"DOOR CLOSURE LOCK INDESIT","atet_code":"","omnia_code":"87440","sku":"NE","price":"","image_url":"http://omniacomponents.s3.eu-west-1.amazonaws.com/images/lambdaresized/500x500/loghi_marchio/Whirlpool/WHIRLPOOL.jpg","description":""},{"name":"DISHWASHER DOOR LOCK - SMEG 697690208 - ORIGINALWith double  microswitch.","atet_code":"148SM08","omnia_code":"INT502SM","sku":"NE - POGLEDATI INT500SM","price":"","image_url":"https://atet-ricambi.it/en/images/148SM08?Size=400x200","description":""},{"name":"DOOR LOCK WHIRLPOOL","atet_code":"","omnia_code":"481227138426","sku":"NE","price":"","image_url":"http://omniacomponents.s3.eu-west-1.amazonaws.com/images/lambdaresized/500x500/loghi_marchio/Whirlpool/WHIRLPOOL.jpg","description":""},{"name":"DISHWASHER DOOR LOCK - SMEG 697690205With double  microswitch.","atet_code":"","omnia_code":"697690205","sku":"2168563","price":"2600","image_url":"","description":""},{"name":"DISHWASHER DOOR LATCH CANDY","atet_code":"148CY12","omnia_code":"41013195","sku":"2165485","price":"1750","image_url":"https://atet-ricambi.it/en/images/148CY12?Size=400x200","description":""},{"name":"DOOR LOCK - BLOMBERG 57715Series: DS 88. 250V 2C-3L 16(4)A closing, 0(0)A  opening. 3L-4 0,5 A. T85, 3 contacts.","atet_code":"148BL02","omnia_code":"INT001BL","sku":"2165981","price":"1890","image_url":"https://atet-ricambi.it/en/images/148BL02?Size=400x200","description":""},{"name":"DOOR LOCK - INDESIT","atet_code":"148ID11","omnia_code":"272452 - NE - POGLEDATI INT014ID","sku":"","price":"","image_url":"https://atet-ricambi.it/en/images/148ID11?Size=400x200","description":""},{"name":"DOOR LOCK - ZANUSSI 1325560017Type: DL-S1, 4 contacts. 4-5:16(6)  closing-opening,250V.","atet_code":"148ZN26","omnia_code":"INT021ZN","sku":"2168564","price":"2600","image_url":"https://atet-ricambi.it/en/images/148ZN26?Size=400x200","description":""},{"name":"DISHWASHER DOOR LOCK - SMEG 697690143 - ORIGINALSeries: DW - ST -  WT.","atet_code":"148SM05","omnia_code":"INT503SM","sku":"2168565","price":"2360","image_url":"https://atet-ricambi.it/en/images/148SM05?Size=400x200","description":""},{"name":"DOOR LOCK INDESIT","atet_code":"","omnia_code":"095979 INT006ID ","sku":"2168455","price":"970","image_url":"http://omniacomponents.s3.eu-west-1.amazonaws.com/images/lambdaresized/500x500/loghi_marchio/Whirlpool/WHIRLPOOL.jpg","description":""},{"name":"GO TO DHL200ID","atet_code":"148ID12","omnia_code":"257618 DHL200ID","sku":"2123685","price":"1630","image_url":"https://atet-ricambi.it/en/images/148ID12?Size=400x200","description":""},{"name":"DOOR LOCK - AEG 1105771024Type: DL-S1. 4-5:18(6) closing-opening, 250V. 4  contacts.","atet_code":"ZAN000001105771024","omnia_code":"INT005AE","sku":"2168566","price":"3070","image_url":"http://omniacomponents.s3.eu-west-1.amazonaws.com/images/lambdaresized/500x500/LAVAGGIO/12_Elettroserrature-Bloccoporta/INT005AE.jpg","description":""},{"name":"DOOR LOCK - BOSCH 633765-619468 - ORIGINAL","atet_code":"148BH08","omnia_code":"INT008BO","sku":"2164878","price":"2830","image_url":"http://omniacomponents.s3.eu-west-1.amazonaws.com/images/lambdaresized/500x500/LAVAGGIO/12_Elettroserrature-Bloccoporta/INT008BO.jpg","description":""},{"name":"DOOR LOCK INDESIT","atet_code":"148HP04","omnia_code":"141683 - NE - POGLEDATI INT002ID","sku":"","price":"","image_url":"https://atet-ricambi.it/en/images/148HP04?Size=400x200","description":""},{"name":"INDESIT WASH MACHINE DOOR LOCK","atet_code":"","omnia_code":"259456","sku":"NE","price":"","image_url":"http://omniacomponents.s3.eu-west-1.amazonaws.com/images/lambdaresized/500x500/loghi_marchio/Whirlpool/WHIRLPOOL.jpg","description":""},{"name":"DRYER DOOR LOCK CANDY","atet_code":"","omnia_code":"97920045","sku":"NE","price":"","image_url":"http://omniacomponents.s3.eu-west-1.amazonaws.com/images/lambdaresized/500x500/loghi_marchio/Candy/Candy_logo.jpg","description":""},{"name":"DOOR LOCK - BOSCH 154077 - BITRONType: BP. 16(6)/250V closing, 1(2)/250V opening. 3  contacts.","atet_code":"","omnia_code":"INT011BO","sku":"2165082","price":"3070","image_url":"http://omniacomponents.s3.eu-west-1.amazonaws.com/images/lambdaresized/500x500/LAVAGGIO/12_Elettroserrature-Bloccoporta/INT011BO.jpg","description":""},{"name":"DISHWASHER DOOR LOCK - ZANUSSI 4055259669 - ORIGINAL2 contacts.","atet_code":"146ZN12","omnia_code":"INT502ZN - NE - POGLEDATI BR. 106","sku":"","price":"0","image_url":"http://omniacomponents.s3.eu-west-1.amazonaws.com/images/lambdaresized/500x500/LAVAGGIO/12_Elettroserrature-Bloccoporta/INT502ZN.jpg","description":""},{"name":"DISHWASHER DOOR LOCK - WHIRLPOOL EX.481241758361","atet_code":"148IG23","omnia_code":"481241758398","sku":"2168567","price":"3660","image_url":"https://atet-ricambi.it/en/images/148IG23?Size=400x200","description":""},{"name":"DOOR LOCK - INDESIT 264535Type: DL-S1.  T85.","atet_code":"","omnia_code":"INT004ID","sku":"2168568","price":"3300","image_url":"http://omniacomponents.s3.eu-west-1.amazonaws.com/images/lambdaresized/500x500/LAVAGGIO/12_Elettroserrature-Bloccoporta/INT004ID.jpg","description":""},{"name":"DOOR LOCK INDESIT","atet_code":"","omnia_code":"275626","sku":"NE","price":"","image_url":"http://omniacomponents.s3.eu-west-1.amazonaws.com/images/lambdaresized/500x500/loghi_marchio/Whirlpool/WHIRLPOOL.jpg","description":""},{"name":"DOOR LOCK WHIRLPOOL","atet_code":"148IG26","omnia_code":"480111104819","sku":"2165394","price":"850","image_url":"https://atet-ricambi.it/en/images/148IG26?Size=400x200","description":""},{"name":"DISHWASHER DOOR LOCK WHIRLPOOL","atet_code":"","omnia_code":"481010792430","sku":"NE","price":"","image_url":"http://omniacomponents.s3.eu-west-1.amazonaws.com/images/lambdaresized/500x500/ORIGINALI/481010792430.jpg","description":""},{"name":"DOOR LOCK BOSCH","atet_code":"","omnia_code":"00438026","sku":"NE","price":"","image_url":"","description":""},{"name":"DOOR LOCK - BOSCH 603514 - ORIGINAL3  contacts.","atet_code":"148BY10","omnia_code":"INT013BO","sku":"2165982","price":"880","image_url":"http://omniacomponents.s3.eu-west-1.amazonaws.com/images/lambdaresized/500x500/LAVAGGIO/12_Elettroserrature-Bloccoporta/INT013BO.jpg","description":""},{"name":"DOOR LOCK - BOSCH 631638 - ORIGINALSeries: DM. 2-1 16(6)A 250V closing. 1(2)A 250V opening. T85, 1E4. 3 contacts.","atet_code":"","omnia_code":"INT018BO","sku":"2168331","price":"4640","image_url":"http://omniacomponents.s3.eu-west-1.amazonaws.com/images/lambdaresized/500x500/LAVAGGIO/12_Elettroserrature-Bloccoporta/INT018BO.jpg","description":""},{"name":"DOOR LOCK - BOSCH 182154 - ORIGINALSeries: DA. 2-3 16(6)A 250V closing. 1(2)A 250V opening. T85, 3 contacts.","atet_code":"148BY09","omnia_code":"INT006BO","sku":"2122054","price":"4670","image_url":"http://omniacomponents.s3.eu-west-1.amazonaws.com/images/lambdaresized/500x500/LAVAGGIO/12_Elettroserrature-Bloccoporta/INT006BO.jpg","description":""},{"name":"DOOR LOCK - BOSCH 605144 - ORIGINALTipo: DL-LC. 10(6), 250V closing. 1(2),  250V opening. 4 contacts.","atet_code":"148BH03","omnia_code":"INT019BO","sku":"2165679","price":"5900","image_url":"http://omniacomponents.s3.eu-west-1.amazonaws.com/images/lambdaresized/500x500/LAVAGGIO/12_Elettroserrature-Bloccoporta/INT019BO.jpg","description":""},{"name":"DOOR LOCK - BOSCH 616876 - ORIGINAL","atet_code":"148BH07","omnia_code":"INT009BO","sku":"2166653","price":"1600","image_url":"https://atet-ricambi.it/en/images/148BH07?Size=400x200","description":""},{"name":"DOOR LOCK - BOSCH 613070 - ORIGINAL250V, 50/60Hz, 3 contacts.","atet_code":"148BH05","omnia_code":"INT007BO","sku":"2165678","price":"4720","image_url":"https://atet-ricambi.it/en/images/148BH05?Size=400x200","description":""},{"name":"DISHWASHER LOCK DOOR HANDLE - INDESIT EX.041239","atet_code":"139AR32","omnia_code":"048970","sku":"2168569","price":"5900","image_url":"http://omniacomponents.s3.eu-west-1.amazonaws.com/images/lambdaresized/500x500/loghi_marchio/Whirlpool/WHIRLPOOL.jpg","description":""},{"name":"DOOR LOCK - WHIRLPOOL 481010474505","atet_code":"148IG31","omnia_code":"481010474505 - NE - POGLEDATI BR. 117","sku":"","price":"","image_url":"https://atet-ricambi.it/en/images/148IG31?Size=400x200","description":""},{"name":"DOOR LOCK INDESIT","atet_code":"","omnia_code":"138989","sku":"NE","price":"","image_url":"http://omniacomponents.s3.eu-west-1.amazonaws.com/images/lambdaresized/500x500/loghi_marchio/Whirlpool/WHIRLPOOL.jpg","description":""},{"name":"DOOR LOCK - WHIRLPOOL 481228058041-DC64-00519AType: T85. 250V, 50/60Hz. 9 contacts. Series AWM,  MAXY, WAB.","atet_code":"148IG24","omnia_code":"INT020WH","sku":"2163766","price":"7900","image_url":"https://atet-ricambi.it/en/images/148IG24?Size=400x200","description":""},{"name":"DOOR LOCK - BOSCH 154077 - ORIGINALSeries: DS88/BS. 250V 3-4 16(6)A closing. 3-4 1A opening. T85, 3 contacts. With release lever.","atet_code":"","omnia_code":"INT002BO","sku":"NE","price":"","image_url":"http://omniacomponents.s3.eu-west-1.amazonaws.com/images/lambdaresized/500x500/LAVAGGIO/12_Elettroserrature-Bloccoporta/INT002BO.jpg","description":""},{"name":"DISHWASHER DOOR LOCK ZANUSSI2 contacts.","atet_code":"146ZN14","omnia_code":"4055283925","sku":"2168570","price":"9450","image_url":"http://omniacomponents.s3.eu-west-1.amazonaws.com/images/lambdaresized/500x500/LAVAGGIO/12_Elettroserrature-Bloccoporta/4055283925.jpg","description":""},{"name":"BOSCH DISHWASHER DOOR LOCK","atet_code":"","omnia_code":"444896","sku":"NE","price":"","image_url":"http://omniacomponents.s3.eu-west-1.amazonaws.com/images/lambdaresized/500x500/loghi_marchio/Bosch/Bosch.jpg","description":""},{"name":"WACHING MACHINE DOOR LOCK - BOSCH 095400-088486","atet_code":"","omnia_code":"088486","sku":"NE","price":"","image_url":"http://omniacomponents.s3.eu-west-1.amazonaws.com/images/lambdaresized/500x500/loghi_marchio/Bosch/Bosch.jpg","description":""},{"name":"DOOR LOCK - SANGIORGIO 32722646 - 57003Series: DS 88. 250V, 2C-3L, 16(4)A closing,0(0)A  opening. T85, 3 contacts.","atet_code":"148SG06","omnia_code":"INT000SG","sku":"2168571","price":"1370","image_url":"https://atet-ricambi.it/en/images/148SG06?Size=400x200","description":""},{"name":"DOOR LOCK - SMEG 814490202","atet_code":"148SM03","omnia_code":"INT001SM","sku":"2168572","price":"1870","image_url":"http://omniacomponents.s3.eu-west-1.amazonaws.com/images/lambdaresized/500x500/loghi_marchio/Smeg/SMEG.jpg","description":""},{"name":"DOOR LOCK - PHILCO 116102866 - ROLD 57776Series: DS 88. 250V, 2C-3L 16(4)A closing,0(0)A  opening. 3L-4 0.5A. 200/250V. T85,4 contacts","atet_code":"","omnia_code":"INT004PH","sku":"NE","price":"","image_url":"http://omniacomponents.s3.eu-west-1.amazonaws.com/images/lambdaresized/500x500/LAVAGGIO/12_Elettroserrature-Bloccoporta/INT004PH.jpg","description":""},{"name":"DOOR LOCK HAIER - ROLD DK040550","atet_code":"148HA02","omnia_code":"INT006HA - NE -POGLEDATI INT004HA","sku":"","price":"","image_url":"https://atet-ricambi.it/en/images/148HA02?Size=400x200","description":""},{"name":"DOOR LOCK - SANGIORGIO 57753","atet_code":"148SG08","omnia_code":"INT006SG","sku":"2168573","price":"1730","image_url":"http://omniacomponents.s3.eu-west-1.amazonaws.com/images/lambdaresized/500x500/LAVAGGIO/12_Elettroserrature-Bloccoporta/INT006SG.jpg","description":""},{"name":"DOOR LOCK HAIER - ROLD DKS40556","atet_code":"","omnia_code":"INT007HA","sku":"NE","price":"","image_url":"","description":""},{"name":"WASHING MACHINE DOOR LOCK - SANGIORGIO DA077055","atet_code":"148SG12","omnia_code":"INT007SG","sku":"2168575","price":"830","image_url":"","description":""},{"name":"DOOR LOCK - INDESIT - ROLD DFF30800","atet_code":"","omnia_code":"INT015ID","sku":"NE","price":"","image_url":"http://omniacomponents.s3.eu-west-1.amazonaws.com/images/lambdaresized/500x500/LAVAGGIO/12_Elettroserrature-Bloccoporta/INT015ID.jpg","description":""},{"name":"DOOR LOCK - WHIRLPOOL 461974200011","atet_code":"","omnia_code":"INT018WH","sku":"NE","price":"","image_url":"http://omniacomponents.s3.eu-west-1.amazonaws.com/images/lambdaresized/500x500/LAVAGGIO/12_Elettroserrature-Bloccoporta/INT018WH.jpg","description":""},{"name":"DOOR LOCK - ZANUSSI","atet_code":"","omnia_code":"8996453073703","sku":"NE","price":"","image_url":"http://omniacomponents.s3.eu-west-1.amazonaws.com/images/lambdaresized/500x500/loghi_marchio/Zanussi/ZANUSSI.jpg","description":""},{"name":"DOOR LOCK - ZANUSSI","atet_code":"","omnia_code":"8996452446728","sku":"NE","price":"","image_url":"http://omniacomponents.s3.eu-west-1.amazonaws.com/images/lambdaresized/500x500/loghi_marchio/Zanussi/ZANUSSI.jpg","description":""},{"name":"DOOR LOCK SMEG","atet_code":"","omnia_code":"817690233","sku":"NE","price":"","image_url":"http://omniacomponents.s3.eu-west-1.amazonaws.com/images/lambdaresized/500x500/loghi_marchio/Smeg/SMEG.jpg","description":""},{"name":"BLOCCOPORTA LVT SMEG","atet_code":"148SM06","omnia_code":"814490983","sku":"NE","price":"","image_url":"https://atet-ricambi.it/en/images/148SM06?Size=400x200","description":""},{"name":"GRUPPO SERRATURA ORIGINALE SMEG","atet_code":"","omnia_code":"697690198","sku":"NE","price":"","image_url":"http://omniacomponents.s3.eu-west-1.amazonaws.com/images/lambdaresized/500x500/loghi_marchio/Smeg/SMEG.jpg","description":""},{"name":"GRUPPO SERRATURA LAVASTOVIGLIE SMEG","atet_code":"146SM01","omnia_code":"697690164","sku":"2168576","price":"1920","image_url":"http://omniacomponents.s3.eu-west-1.amazonaws.com/images/lambdaresized/500x500/loghi_marchio/Smeg/SMEG.jpg","description":""},{"name":"GRUPPO SERRATURA ORIGINALE SMEG","atet_code":"146SM02","omnia_code":"697690154","sku":"2168577","price":"1920","image_url":"http://omniacomponents.s3.eu-west-1.amazonaws.com/images/lambdaresized/500x500/loghi_marchio/Smeg/SMEG.jpg","description":""},{"name":"GRUPPO SERRATURA ORIGINALE SMEG","atet_code":"","omnia_code":"697690142","sku":"NE","price":"","image_url":"http://omniacomponents.s3.eu-west-1.amazonaws.com/images/lambdaresized/500x500/loghi_marchio/Smeg/SMEG.jpg","description":""},{"name":"GRUPPO SERRATURA SMEG 697690139","atet_code":"","omnia_code":"697690139","sku":"NE","price":"","image_url":"http://omniacomponents.s3.eu-west-1.amazonaws.com/images/lambdaresized/500x500/loghi_marchio/Smeg/SMEG.jpg","description":""},{"name":"OUT OF PRODUCTION","atet_code":"","omnia_code":"651001954","sku":"NE","price":"","image_url":"http://omniacomponents.s3.eu-west-1.amazonaws.com/images/lambdaresized/500x500/loghi_marchio/Ardo/Ardo.png","description":""},{"name":"DOOR LOCK - BOSCH 636708 - ORIGINAL","atet_code":"148BH10","omnia_code":"636708","sku":"2168578","price":"2400","image_url":"http://omniacomponents.s3.eu-west-1.amazonaws.com/images/lambdaresized/500x500/loghi_marchio/Bosch/Bosch.jpg","description":""},{"name":"DOOR LOCK BOSCH","atet_code":"","omnia_code":"629580","sku":"NE","price":"","image_url":"","description":""},{"name":"DOOR LOCK - BOSCH","atet_code":"","omnia_code":"627610","sku":"NE","price":"","image_url":"http://omniacomponents.s3.eu-west-1.amazonaws.com/images/lambdaresized/500x500/loghi_marchio/Bosch/Bosch.jpg","description":""},{"name":"WASHING MACHINE DOOR LOCK - BOSCH 627557 - ORIGINAL","atet_code":"148SM06","omnia_code":"627557","sku":"NE","price":"","image_url":"https://atet-ricambi.it/en/images/148SM06?Size=400x200","description":""},{"name":"DOOR LOCK - BOSCH","atet_code":"","omnia_code":"618981","sku":"NE","price":"","image_url":"http://omniacomponents.s3.eu-west-1.amazonaws.com/images/lambdaresized/500x500/loghi_marchio/Bosch/Bosch.jpg","description":""},{"name":"DOOR LOCK MIELE","atet_code":"","omnia_code":"5712492","sku":"NE","price":"","image_url":"http://omniacomponents.s3.eu-west-1.amazonaws.com/images/lambdaresized/500x500/loghi_marchio/Miele/MIELE.jpg","description":""},{"name":"DOOR LOCK GORENJE","atet_code":"","omnia_code":"550241","sku":"NE","price":"","image_url":"http://omniacomponents.s3.eu-west-1.amazonaws.com/images/lambdaresized/500x500/loghi_marchio/Gorenje/GORENJE.jpg","description":""},{"name":"WASHING MACHINE DOOR LOCK MIELE","atet_code":"","omnia_code":"4842085","sku":"NE","price":"","image_url":"http://omniacomponents.s3.eu-west-1.amazonaws.com/images/lambdaresized/500x500/loghi_marchio/Miele/MIELE.jpg","description":""},{"name":"DOOR LOCK MIELE","atet_code":"","omnia_code":"4837752","sku":"NE","price":"","image_url":"http://omniacomponents.s3.eu-west-1.amazonaws.com/images/lambdaresized/500x500/loghi_marchio/Miele/MIELE.jpg","description":""},{"name":"DISHWASHER DOOR LOCK  - BOSCH 423936 - ORIGINAL","atet_code":"","omnia_code":"423936","sku":"NE","price":"","image_url":"http://omniacomponents.s3.eu-west-1.amazonaws.com/images/lambdaresized/500x500/loghi_marchio/Bosch/Bosch.jpg","description":""},{"name":"ZANUSSI DISH WASHER HANDLE","atet_code":"148ZN13","omnia_code":"3792030342","sku":"NE","price":"685","image_url":"https://atet-ricambi.it/en/images/148ZN13?Size=400x200","description":""},{"name":"DOOR LOCK BEKO","atet_code":"148AC07","omnia_code":"2805310500","sku":"2166522","price":"620","image_url":"https://atet-ricambi.it/en/images/148AC07?Size=400x200","description":""},{"name":"BOSCH DOOR SWITCH 168671","atet_code":"","omnia_code":"168671","sku":"NE","price":"","image_url":"http://omniacomponents.s3.eu-west-1.amazonaws.com/images/lambdaresized/500x500/loghi_marchio/Bosch/Bosch.jpg","description":""},{"name":"DOOR RETARDER EX.1297479055","atet_code":"148ZN21","omnia_code":"1462229145 INT009ZN OK","sku":"2125360","price":"1090","image_url":"https://atet-ricambi.it/en/images/148ZN21?Size=400x200","description":""},{"name":"DOOR LOCK ZANUSSI","atet_code":"","omnia_code":"1249675008","sku":"NE","price":"","image_url":"http://omniacomponents.s3.eu-west-1.amazonaws.com/images/lambdaresized/500x500/loghi_marchio/Zanussi/ZANUSSI.jpg","description":""},{"name":"DOOR LOCK ZAN 1105362006","atet_code":"ZAN000001105362006","omnia_code":"1105362006","sku":"NE","price":"","image_url":"http://omniacomponents.s3.eu-west-1.amazonaws.com/images/lambdaresized/500x500/loghi_marchio/Zanussi/ZANUSSI.jpg","description":""}]
